{"D11": {"instagram": "https://www.instagram.com/0_00jakup", "intro": "평범한 일상"}, "D35": {"website": "115room.kr", "intro": "우리가 좋아하는 공간, 115room"}, "M19": {"instagram": "instagram.com/201_illust", "website": "201illust.com", "intro": "현실과 비현실 사이의 소녀들을 디지털 일러스트로 담아내고 있습니다."}, "A19": {"instagram": "www.instagram.com/365_atelier", "intro": "365탄생화 일러스트를 매개로 다양한 굿즈 작업과 출간 작업을 하고 있어요"}, "H32": {"instagram": "https://www.instagram.com/423heehee/", "intro": "안녕하세요! 순간을 기록하는 423희희입니다."}, "E05": {"instagram": "https://www.instagram.com/ga.wool", "website": "https://notefolio.net/ga_wool", "intro": "세상의 빛나는 순간을 기록하는 일러스트레이터이자 여행가.\n20개국 55개 도시를 느린 속도로 여행하며 모아온 다정한 순간들을 글과 그림으로 기록해 나누고 있다."}, "C33": {"instagram": "www.instagram.com/bygajee", "website": "www.bygajee.com", "intro": "한국 전통문화를 재해석한 디지털 페인팅 작업을 합니다.\n십이지를 포함한 동물을 즐겨 그립니다.\n개인 창작 활동과 더불어 여러 기업, 기관과 다양한 영역에서 협업하고 있습니다."}, "Q19": {"instagram": "https://www.instagram.com/ganbare_nonochan_kr/", "intro": "인스타툰 『간바레! 노노짱』연재중."}, "M43": {"instagram": "https://www.instagram.com/gya.oon", "intro": "아포와 가토의 말랑콩떡한 이야기를 담는 갸운입니다."}, "O52": {"instagram": "https://www.instagram.com/reno_toon", "website": "https://www.gunwoofriends.com", "intro": "한국 전통 소재와 멸종 위기 동물을 한국적 팝아트로 재미있게 그리는 작가입니다."}, "J01": {"instagram": "https://www.instagram.com/blacksandforest/"}, "R47": {"instagram": "https://www.instagram.com/getkoustudio/", "intro": "From Space to Earth, GETKOU!!\n우주에서 지구로 불시착한 외계 도마뱀 친구들 '겟코우' 입니다!"}, "M26": {"instagram": "https://www.instagram.com/dawnitive.wave?igsh=MW1ldjRkaXhqYnR2Yg==", "intro": "서늘한 결을 그립니다."}, "Q48": {"instagram": "https://www.instagram.com/kkyul_jmt/", "intro": "베니, 밤갱, 양갱 고양이 세 마리와 집사의 털 날리는 일상툰 | 인스타툰 연재중 | 캐릭터 디자인 | 굿즈 제작 | 콘텐츠 제작"}, "I36": {"instagram": "https://www.instagram.com/gogojodam", "website": "https://smartstore.naver.com/gogojodam", "intro": "작은 존재가 주는 따뜻함을\n나무 조각에 담고 있습니다."}, "T05": {"instagram": "https://www.instagram.com/babgobong", "website": "x.com/babgobong", "intro": "고양이+🍚(米).. \n쌀고양이 친구들의 이야기를 그려요  ( ́⌒ .̫ ⌒ ̀)"}, "G26": {"instagram": "https://www.instagram.com/godongsang/?hl=ko", "website": "https://notefolio.net/godongsang", "intro": "고-양이와 동-그란 세-상\n\n각진 세상도 고양이와 함께면 - 동글동글해지는 법이니까요🪽"}, "L26": {"instagram": "https://www.instagram.com/gorani83?igsh=OHJlc2lpenplbmR2&utm_source=qr", "intro": "수채화 수작업 일러스트레이터 고라니 입니다."}, "F10": {"instagram": "https://www.instagram.com/fromkosanta", "website": "https://www.kosanta.kr", "intro": "What ever you do, wherever you go\n365 days of christmas!"}, "G12": {"instagram": "https://www.instagram.com/seoda.ko?igsh=ZmtvdTZtdXhwbnds&utm_source=qr", "intro": "이름 없는 감정을 그립니다"}, "K13": {"instagram": "https://www.instagram.com/goeun_her/", "intro": "곁에, 오래머물길.\n일러스트레이터 고은입니다.\n\ngoeun.03130@gmail.com"}, "Q15": {"instagram": "https://www.instagram.com/kohxxr.iiii?igsh=ZW5hdzJyOHNycmUx&utm_source=qr", "website": "https://youtube.com/@kohxxriiii?si=PD65I2p9Tfq538dO", "intro": "KOHYORI Illustrator & Character Artist | 미소년 좋아하세요?"}, "Q04": {"instagram": "https://www.instagram.com/golden.hour_k/", "website": "https://www.artstation.com/mj_kim", "intro": "게임회사 배경원화 경력에서 프리랜서 일러스트레이터로 전향."}, "G31": {"instagram": "https://www.instagram.com/gongdeun_/", "website": "https://smartstore.naver.com/gongdeun_", "intro": "따뜻한 햇살을 한가득 그림에 담아내고 싶은 공든입니다."}, "L47": {"instagram": "https://www.instagram.com/0sari222", "intro": "<공사리>는 식물과 사물 등 일상 속 풍경을 따뜻한 시선으로 담아내는 일러스트 브랜드입니다. 원화와 굿즈를 통해 작은 순간 속 자연의 위로와 여유를 전합니다."}, "C22": {"instagram": "https://www.instagram.com/gwak.bukku", "intro": "안녕하세요. 귀여운게 세상을 구한다! 곽부꾸입니다."}, "J20": {"instagram": "https://www.instagram.com/inmroomy?igsh=MTBqNmRmYXR0Ym9nNQ==", "website": "https://inmroomy.myportfolio.com/", "intro": "일상 속에서 느낀 감정, 찰나의 순간들, 말로 다 담기 어려운 마음들을 꺼내어 포근한 그림으로 표현한 공간입니다."}, "M30": {"instagram": "https://www.instagram.com/guri__ming", "website": "https://litt.ly/guriming", "intro": "몽글몽글 꿈같은 일상과 소녀들을 그려요\n“ Have a gurimingDay-‧∘˳°∗˚ ”"}, "I04": {"instagram": "https://www.instagram.com/guwol_", "website": "https://naver.me/5du3CLgw", "intro": "소소한 일상을 그림에 담는\n일러스트레이터 구월 입니다."}, "G47": {"instagram": "https://www.instagram.com/dmadameb/", "intro": "안녕하세요, 시간을 녹여 색연필로 고운 그림책을 짓는 귀부인b입니다."}, "M52": {"instagram": "https://www.instagram.com/guiyoung_920/", "website": "https://x.com/guiyoung_920?s=20"}, "K33": {"instagram": "https://www.instagram.com/greeda.jy", "intro": "자연을 보고 느끼고 그리는 일러스트레이터 그리다입니다.  자연속에서 마음의 따듯한 위로를 받으며 행복과 편안함으로 휴식할 수 있는 그림을 그립니다."}, "Q03": {"instagram": "https://www.instagram.com/thestoryof_goodtree/?igsh=Mng0dXMxaHhrNmRi&utm_source=qrv", "intro": "바다의 물감으로 하늘 캔버스에 편지를 그리는 작가\n\n\n\n개인전 9 회\n다수의 그룹 전시 참여"}, "N04": {"instagram": "https://www.instagram.com/grium_riu/", "website": "https://litt.ly/grium_riu", "intro": "일상과 상상을 인물 위주로 표현하며 일러스트, 만화, 웹툰, 각색콘티, 디자인, 영상 등 다양한 분야에서 N잡 일러스트레이터로 활동하고 있습니다."}, "L27": {"instagram": "instagram.com/griko.jiin", "website": "grikojiin.notion.site", "intro": "꿈, 희망, 사랑 이야기가 담긴\ngraphic poem"}, "P03": {"instagram": "https://www.instagram.com/mjhappylaughter/"}, "J23": {"instagram": "https://www.instagram.com/aitch8h", "website": "https://blog.naver.com/2cathouse", "intro": "스쳐 지나가는 감정과 조용한 장면들을 글과 그림으로 기록하고, 손에 잡히는 형태로 엮어냅니다."}, "I13": {"instagram": "https://www.instagram.com/grim_grit/", "intro": "매 순간마다 바람 냄새, 하늘 색, 빛의 조각이 다릅니다. \n마음에 동요를 주는 순간들을 잡아두고 싶어 \n그림을 그리는 그림그릿입니다."}, "E16": {"instagram": "https://www.instagram.com/glen_object", "intro": "어디에나 사용하기 좋은 감성적인 디자인 문구류를 디자인 및 제작, 판매를 하고 있습니다."}, "U18": {"instagram": "https://www.instagram.com/glitting._official/", "website": "https://smartstore.naver.com/glitting", "intro": "안녕하세요! 반짝이는 취미생활을 만드는 저희는 글리팅입니다✨ 바쁜 하루 속 나를 위한 반짝이는 쉼표를 더해보세요!💖"}, "K36": {"instagram": "https://instagram.com/cloudynine", "website": "https://heather-parent-35e.notion.site/cloudynine-2025-100636db6c1a80dab8dce626f232cc09", "intro": "여러분의 귀여움은 무엇인가요?\n\n귀여움으로 세상을 구하는 김구구입니다.\n\n평면에 물성을 담아내는 작업을 이어가고 있습니다."}, "I15": {"instagram": "https://www.instagram.com/kim.dotu", "intro": "일상의 관찰과 상상을 그립니다."}, "L50": {"website": "https://blog.naver.com/kimlaegon911", "intro": "안녕하세요, 고요한 선과 반짝이는 색을 그리는 일러스트레이터 김래곤입니다. 어지럽고 복잡한 마음이 깊게 잠길 수 있는 작업을 바라며, 이야기 있는 그림을 쓰고 있습니다."}, "G43": {"instagram": "https://www.instagram.com/ssujung.kim/", "website": "https://www.ssujungkim.com/", "intro": "일상에서 만난 순간들을 그림으로 기록하고 있습니다"}, "K28": {"instagram": "https://www.instagram.com/kim_sswang", "website": "https://kimsswang.creatorlink.net/", "intro": "마카, 도자기와 판화로 주변에 이미 존재하고 있는 행복을 표현합니다.\n\nMarker Illustrator/Novice Potter&Printmaker"}, "L32": {"instagram": "https://www.instagram.com/suerteyu", "website": "https://blog.naver.com/realmead", "intro": "애정으로 넓어지는 세계♥️\n자세한 내용은 블로그에 있어요✨"}, "I34": {"instagram": "https://www.instagram.com/dingdookim", "website": "www.dingdookim.com", "intro": "단순하지만 따뜻한 그림을 그려요"}, "N27": {"website": "https://kimconch.com", "intro": "환상의 섬에서 일어나는 작은 이야기들을 담아요"}, "F17": {"instagram": "https://www.instagram.com/drawing_j2/", "intro": "회화와 디자인작업을 함께 합니다.\n소소한 일상의 행복과 사랑을 담아 그려요."}, "U19": {"instagram": "https://www.instagram.com/carandache.kr/?hl=ko", "website": "www.carandache.co.kr", "intro": "SINCE 1915 | SWISSMADE\n스위스 프리미엄 필기구&화방용품 전문기업 까렌다쉬입니다."}, "O15": {"instagram": "https://www.instagram.com/bb_birdyan", "website": "https://grafolio.ogq.me/profile/Kkambonyangeee/project", "intro": "누구나 마음속에 품고 있는 마음 속 까만 고양이, 깜보냥이"}, "F18": {"instagram": "instagram.com/qoover_ofc"}, "C18": {"instagram": "https://www.instagram.com/cong_cafe", "intro": "나꽁아꽁은 추억을 보관하는 일을 하는 브랜드입니다.\n우리가 기록하지 않으면 잃어버릴 수 있는 작은 시간과 풍경, 자연을 담아 그림을 그리고 제품을 제작합니다."}, "I37": {"website": "https://nariillust.myportfolio.com/", "intro": "그림을 그리고 디자인을 하는 일러스트레이터 나리입니다.\n 디자인의 20년 넘는 경력을 가지고 있으며 현재는 프리랜서로 디자인 작업과 함께 일러스트 작가로 활동하고 있습니다."}, "H45": {"instagram": "https://www.instagram.com/nasol_2016", "intro": "모든것이 빠르게 변해가는 일상\n그 한순간을 느리게 포착해서\n따뜻하고 편안한 느낌으로 표현하려 합니다."}, "G28": {"instagram": "https://www.instagram.com/naomi_illustrator?igsh=MWprYXdqazFsY296NQ%3D%3D&utm_source=qr", "intro": "따뜻한 순간을 그립니다."}, "J19": {"instagram": "https://www.instagram.com/nightynight_zz/", "intro": "🛏️잠들기 전 읽는 동화 속 일러스트 / \n포근한 이불 속, 눈을 감기 전\n마음에 살짝 내려앉는 동화 속 세상을 그립니다."}, "J12": {"instagram": "https://www.instagram.com/night_lights217_drawing/"}, "L24": {"instagram": "https://www.instagram.com/gunieon?igsh=MTVzemVta2hzc21xOA%3D%3D&utm_source=qr", "intro": "어느날,갑자기 내가 읽던 로판 속 주인공들이 내 방으로 떨어졌다.어린데다 갈 곳 없는 아가씨들이니 잠은 재워주겠지만-밥벌이는 스스로 해라,영애들이여!"}, "M40": {"instagram": "www.instagram.com/nyamnyam_illust", "intro": "장난꾸러기 남매고양이 쿠키와 레오, 다양한 고양이들을 그리는 냠냠스튜디오입니다. 스티커, 스탬프 등 문구류부터 파우치, 가방, 티셔츠, 키링 등 귀여운 고양이 제품들을 만나보세요!"}, "S06": {"instagram": "https://www.instagram.com/meo_monsters", "intro": "무해한 행복을 드려요!"}, "F08": {"website": "https://smartstore.naver.com/mewmewbeam_world", "intro": "냥냥빔의 이야기를 그리고 담아 여행자를 위한 문구를 만듭니다. Only for travelers"}, "V26": {"instagram": "https://www.instagram.com/nyangwoon", "website": "https://nyangwoon.com/", "intro": "신비한 외계고양이 냥운.\n좌충우돌 지구 적응기, 현재 진행 중…👀🐾"}, "R45": {"instagram": "https://instagram.com/wwwneverthelesscom", "website": "https://smartstore.naver.com/nevertheless_studio", "intro": "그럼에도 불구하고, 기록하고 싶은 날들을 위한 제품을 만듭니다 ♡"}, "H19": {"instagram": "https://www.instagram.com/neon.pastell/", "website": "https://neonpastell.creatorlink.net/", "intro": "차원소녀들을 주제로, 고딕키치한 일러스트와 그래픽디자인을 결합해 여러 차원을 그려나가고 있으며,\n차원 스토리들로 여러 차원의 잔재(굿즈)들을 제작하고 있습니다"}, "R41": {"instagram": "https://www.instagram.com/ruka_neonpicnic/", "intro": "컬러풀한 일상 속 작은 피크닉같은 감성을 담는 네온피크닉 입니다.\n시티팝과 90년대 레트로 무드를 다양한 색감으로 재해석한 작품을 그립니다."}, "O19": {"instagram": "https://www.instagram.com/1004sohyunnetty", "intro": "세상엔 무수히 많은 색이 있듯이 삶에도 무수히 많은 삶의 방식이 있습니다. 내가 선택한 삶의 색은 어떤 모습일까? 색이 섞이고 섞이는 모습은 표현합니다. 시시각각 변하는 얼굴에서"}, "D27": {"website": "nonotnever.kr", "intro": "오늘 하루도"}, "N26": {"instagram": "https://instagram.com/mooolung_e", "intro": "세상을 물렁하게 살아가는 물렁이입니다. Let's 물렁!"}, "F28": {"instagram": "https://www.instagram.com/noorie.watercolours/", "intro": "반짝이는 매 순간!"}, "K54": {"instagram": "https://www.instagram.com/nuy_illust/", "website": "https://linktr.ee/NUY_", "intro": "일러스트레이터 누이입니다."}, "N25": {"instagram": "https://www.instagram.com/newstoon556/", "website": "https://contents.premium.naver.com/newstoon556/newstoon", "intro": "안녕하세요 뉴스툰입니다!　　　　　　　　　　　　　　　협업문의 triarii762@gmail.com"}, "N19": {"instagram": "https://www.instagram.com/33_808/?hl=ko"}, "K41": {"instagram": "https://www.instagram.com/nuru._.ccavy/", "intro": "한국의 전통과 한국 도깨비 ' 느루깨비'를 통해서  작가 '시니'가 운영하는 전통적이고 힙한 그림을 그리는 브랜드입니다. 전통과 현대를 잇는 작은 다리가 되기를 바랍니다."}, "D14": {"website": "www.zero523.com"}, "M24": {"instagram": "https://www.instagram.com/from_niro", "intro": "햇살처럼 따듯한 그림을 그립니다."}, "E34": {"instagram": "https://www.instagram.com/all31dakki/", "intro": "현대인의 억눌린 감정을 대신 표현하는 네모토끼 ‘다끼’와\n이를 위로하는 욕받이인형 ‘다욕이’를 통해 MZ세대의 정서와 깊은 공감을 담아내는 \n감정공감형 캐릭터 IP 기업입니다."}, "T36": {"instagram": "https://www.instagram.com/kim_yudal/", "website": "https://blog.naver.com/ivysquare1", "intro": "여행이 좋고 맛있는 것은 더 좋은 수달, 유달이와 똑부러진 작은 오리 올리의 이야기를 그립니다."}, "R36": {"instagram": "https://www.instagram.com/dani_store_o_o", "intro": "귀여운 실버푸들 먼지와 닥스훈트 달이의 우당탕탕 일상 스토리"}, "L28": {"instagram": "https://www.instagram.com/dahye.kkk", "intro": "안녕하세요. 일러스트레이터 다혜입니다. \n인물 중심의 일러스트와 감정이 담긴 표정과 분위기를 그려내는 데 집중하고 있습니다."}, "L16": {"instagram": "https://www.instagram.com/dali_design101_/", "website": "https://link.inpock.co.kr/dali_illust?utm_source=ig&utm_medium=social&utm_content=link_in_bio", "intro": "잊을 수 없는 순간을 그리는 일러스트레이터 달리입니다 :)"}, "D10": {"instagram": "https://www.instagram.com/dambit_74", "intro": "상상속의 풍경을 먹으로 그려요.\n\"Paint an imagined landscape in the style of Korean art.\""}, "C20": {"instagram": "instagram.com/dami_grim", "intro": "Always beside you"}, "R09": {"instagram": "https://www.instagram.com/damjang.alae/", "website": "https://x.com/alae_damjang", "intro": "별다를 것 없어보이는 풍경도 어느새 특별한 날. \n그 순간에 떠오르는 상상을 그립니다."}, "P24": {"instagram": "https://www.instagram.com/dc_worm/", "intro": "대충벌레와김겨자"}, "M23": {"instagram": "https://www.instagram.com/daemrawing/", "website": "https://smartstore.naver.com/daemrawing", "intro": "잔잔한 공감으로 위로를 전합니다."}, "O20": {"instagram": "https://www.instagram.com/lemon_hama/", "intro": "공두리# X 반애 BANAE의 콜라보!\n여름 서일페에서 만나요!"}, "K18": {"instagram": "www.instagram.com/thedrawinghand.viva/", "intro": "그림 그리는 사람\n런던에 시작한 그리는 삶은 서울을 거쳐, 현재 스페인 빌바오에서 계속 이어지고 있습니다."}, "P50": {"instagram": "https://www.instagram.com/the_sllo", "intro": "‘슬로’는 귀여움을 넘어 소외된 이들까지 연결하는 메시지를 담고 있습니다. 이를 통해 세상과 소통하며 위로를 얻고, 느린 속도 속에서도 서로를 향해 함께 나아갈 수 있기를 바랍니다"}, "E35": {"instagram": "https://www.instagram.com/thepuri_village/", "website": "https://smartstore.naver.com/thepuri_village", "intro": "요술봉을 든 영웅 토끼 러뚜뚜가 친구들을 장난으로부터 지켜주는, 기발하고 마법적인 세계. 장난스러운 모험과 독창적이며 화려한 매력이 어우러져 있습니다."}, "Q38": {"instagram": "https://www.instagram.com/dumbdum_toon/", "website": "https://comic.naver.com/webtoon/list?titleId=841876&tab=sun", "intro": "네이버웹툰 <덤벙덤벙 내 인생>의 덤덤입니다!"}, "B11": {"instagram": "https://www.instagram.com/chunky.chunks/", "intro": "\"매력덩어리 귀염덩어리\"\n\n부드러운 하얀 반죽에서 노릇하게 구워진 도자기 덩어리들.\n도자기의 무한한 표현력으로 세상 귀여운 생명체를 빚습니다."}, "D40": {"instagram": "https://www.instagram.com/daol_palette/?hl=ko", "intro": "🏠비 오는 날 젖기 시작한 이끼 낀 돌 담장과\n그 사이를 비집고 길가로 드리운 들꽃.🌷\n들여다보고 귀 기울이면 보이는 포근한 도깨비 화방입니다."}, "O33": {"instagram": "https://www.instagram.com/donachodiary/"}, "C21": {"instagram": "https://www.instagram.com/doneory/", "website": "https://x.com/Doneory", "intro": "안녕하세요! 도너리입니다."}, "H03": {"instagram": "www.instagram.com/otamot.studio", "intro": "틈메이로와 인생이야기를 풀어나가는 도둡입니다"}, "M09": {"instagram": "https://www.instagram.com/dorang413/", "website": "https://mongle.kr/", "intro": ":)"}, "V45": {"instagram": "https://www.instagram.com/domi__i/", "website": "https://x.com/domi___i", "intro": "도미월드 세계에 어서오세요."}, "F38": {"instagram": "www.instagram.com/dom_doming", "website": "https://twitter.com/dom_doming", "intro": "이상한 환상들과 그 모호한 형태를 그리고, 이야기를 씁니다.\n환상동화 풍의 개인적 그림 세계를 기반으로 하는\n아트브랜드 '이오환상곡'을 운영하고 있습니다.\n\n저서: 기묘한 병 백과"}, "L45": {"instagram": "https://www.instagram.com/dosoon_toon/", "website": "https://litt.ly/kimdosoon", "intro": "일상을 그리고 있습니다."}, "P51": {"instagram": "https://www.instagram.com/dott.k.illustration/", "intro": "네모난 과일과 동물들을 그리는 걸 좋아합니다. 조금 하찮지만 사랑스러운 틈새 이야기를 그립니다. 주로 여러 핸드 드로잉 질감들을 모아 디지털 콜라주 작업을 합니다."}, "P23": {"instagram": "https://www.instagram.com/dohwa.earth/", "website": "https://comic.naver.com/community/u/Dohwa", "intro": "계절의 단편을 그리는 도화입니다."}, "J50": {"instagram": "https://www.instagram.com/username.dok", "intro": "도화지에 볼펜으로 그립니다"}, "R39": {"instagram": "https://www.instagram.com/dsmhana", "intro": "ㄱㅜㅣㅇㅕㅇㅜㄴㅇㅣㅇㅑㄱㅣㄹㅡㄹㄱㅡㄹㅕㅇㅛ!"}, "L06": {"instagram": "www.instagram.com/grim.gle_dubu", "website": "https://youtube.com/@dubu_studio", "intro": "애정하는 모든 순간을 담아요."}, "D20": {"instagram": "https://www.instagram.com/doolip_doodle/"}, "L48": {"instagram": "https://www.instagram.com/keem_daye", "intro": "[둥한 순간]\n고양이 둥이의 소소한 일상을 그립니다."}, "I33": {"instagram": "https://www.instagram.com/_duim_/", "intro": "일상 속 포근하고 귀여운 친구들을 그려요"}, "I41": {"instagram": "www.instagram.com/du_plicity", "intro": "일러스트레이터 겸 패션디자이너 \n\n'누구나 이중성은 있다'\n\n전통 구담과 민담을 각색하여 다양성이 담긴,\n재미있는 스토리가 있는 것들을 만듭니다."}, "V47": {"instagram": "https://www.instagram.com/drawingday.kr/", "website": "https://smartstore.naver.com/drawingday/products/13623283209", "intro": "털복숭이 친구와 함께하는 일상이야기를 그립니다."}, "D26": {"instagram": "https://www.instagram.com/mosla_greem/", "intro": "<함께 사랑하고 놀다가는 삶을 꿈꿉니다>\n저는 동물을 사랑합니다. 특히 개를 매우 사랑해요!"}, "L13": {"instagram": "www.instagram.com/thistimesu", "intro": "안녕하세요. 흑백 그림 그리는 일러스트레이터 수(thistimesu)입니다."}, "U09": {"instagram": "https://www.instagram.com/dia_rium/", "intro": "17년째 그림만 그리는사람"}, "A09": {"instagram": "https://www.instagram.com/dear._is_letter_shop/", "website": "https://mkt.shopping.naver.com/link/6843fab28dd273404b731a00", "intro": "Dear.는 편지지 전문 브랜드로 평범함을 넘어 취향과 감각이 담긴 독특하고 재밌는 제품을 판매합니다. 마음을 전하는 순간을 더 특별하게, 사랑하는 사람과의 일상을 기록해 보세요."}, "E19": {"instagram": "https://www.instagram.com/this_is_yeongy"}, "D38": {"instagram": "https://www.instagram.com/dear_my_dolly/", "intro": "오래된 장난감 가게 선반 뒤에 자리한\n동화 속 작은 장난감 세상\n\n디어돌리에 어서오세요!"}, "Q22": {"instagram": "www.instagram.com/dear.my.ha", "website": "https://m.smartstore.naver.com/dear-my-ha", "intro": "[디어마이하]\n사랑 가득 행복을 전합니다.\nDEAR MY HA-PPINESS : 나의 행복에게."}, "R51": {"instagram": "https://www.instagram.com/dear__town/", "intro": "소중한 것들이 모이는 곳, 디어타운을 꾸려나가며 작업하고 있어요"}, "V33": {"instagram": "https://www.instagram.com/design_meaning", "website": "https://designmeaning.creatorlink.net/", "intro": "\"유의미한 보는 즐거움, 디자인 미닝\"\n-\n한국의 유물과 전통 문화를 활용한 미닝만의 유니크한 아트웍을 경험해 보세요!"}, "N44": {"instagram": "https://www.instagram.com/diji_planet", "website": "https://inabooth.io/characters/INB-WBY-N2MD?fbclid=PAZXh0bgNhZW0CMTEAAafWTgfrLRSClcw0KrLchS0X2ha2Wcwdohc9qYy5VczhgkhTooQ72z96NwyayQ_aem_II7S2k5TZlKrcD9uVcprhg", "intro": "말랑말랑하고! 빵빵한 외형! 어디를 보고, 무슨 생각을 하는지 도저히 모를 눈의 '또루루(DDORURU)'! 디지행성에서 펼쳐지는 또루루의 우당퉁탕 여행일지, 같이 가봐요!"}, "P54": {"instagram": "https://www.instagram.com/ding.gul_daeng.gul/", "intro": "시골집 강아지를 모티브로 한 강아지 캐릭터 미숫가루 '미루'와 시루떡 '시루'의 이야기를 그립니다."}, "B17": {"instagram": "https://www.instagram.com/_berryheart/", "website": "https://smartstore.naver.com/_berryheart", "intro": "사랑스러운 딸기의 마음을 담아 만드는 문구"}, "J36": {"instagram": "https://www.instagram.com/talbi_illust", "website": "https://www.facebook.com/talbi1004", "intro": "사인펜으로 음식 일러스트를 그리는 딸비입니다.\n음식과 동물들이 조화로운 일상과 동물들이 가게를 운영하는 '음식마을'이라는 컨셉으로 맛있고 따뜻한 그림을 그리고 있습니다."}, "I43": {"instagram": "https://www.instagram.com/ttang_studio", "website": "https://smartstore.naver.com/ttang_studio", "intro": "ⓣⓣⓐⓝⓖ•ⓢⓣⓤⓓⓘⓞ\n\n땅 위에 사는 작은친구들을 그려요(ᵔ.ᵔ)"}, "G46": {"instagram": "https://www.instagram.com/ddoddo.friends/", "website": "https://blog.naver.com/everistudio", "intro": "강아지 또야와 친구들의 얼렁뚱땅 귀여운 일상을 그립니다♡ \n\n오늘도 또또 행복하세요~"}, "H07": {"instagram": "https://www.instagram.com/dddingddong/", "intro": "낯은 가리지만 다정한 마음을 지닌 소심한고양이들입니다.\n따뜻한 귀여움이 담긴 일상을 그립니다."}, "P11": {"instagram": "https://www.instagram.com/_lano_world?igsh=MW50cG9reDhsaTlwdA%3D%3D&utm_source=qr", "intro": "밀라노에서 온 고양이 라노와 그의 친구들이 그려내는 \n귀염고 깜찍한 스토리가 있는 라노월드입니다."}, "Q54": {"instagram": "http://www.instagram.com/ramo.toon", "intro": "안녕하세요. \n작고 소중한 일상을 그리는 인스타툰 작가 라모입니다.\n공감되는 일상부터 알바 썰, 귀여운 일러스트를 그립니다!"}, "R22": {"instagram": "https://www.instagram.com/ramiway_planet?igsh=MWJlbzA1MTMwZWJrbA==", "website": "https://smartstore.naver.com/ramiway", "intro": "귀여움으로 힐링하는 라미웨이 입니다:)\n\n집순이 살찐 토끼 '라밍이'와 만두만 먹어서 얼굴이 만두모양으로 변한  아기 고양이 '찌만이'가 주캐릭터 입니다."}, "S28": {"instagram": "https://www.instagram.com/lovu.world/", "intro": "사랑이 가득한 라뷰월드"}, "R28": {"instagram": "https://www.instagram.com/rayeonfancy/", "website": "https://smartstore.naver.com/rayeon86", "intro": "오늘도 반짝반짝 귀여운 하루!"}, "I03": {"instagram": "www.instagram.com/la_fille_de_paris__/", "intro": "﻿짧지만 길었던 파리와 런던에서의 생활을 추억 하며,  추억의 이야기를 일러스트로 표현해 보았다."}, "F22": {"instagram": "https://www.instagram.com/lalangheej/", "website": "https://x.com/lalangheej", "intro": "소녀들의 꿈 같은 일상과 비일상을 그리는 랄랑입니다. \"댄스플로어\"를 큰 주제로 삼아, 춤추는 인물들의 움직임과 그로 인한 바람을 느낄 수 있는 그림을 보여드리고자 합니다!"}, "N37": {"instagram": "https://www.instagram.com/ramniverse", "intro": "귀여움이 가득한 새로운 우주🌟"}, "R13": {"instagram": "https://www.instagram.com/rang_lua?igsh=MTM4MnE1bTFteG1kdQ%3D%3D&utm_source=qr"}, "O47": {"instagram": "https://www.instagram.com/love.crescent/", "website": "https://smartstore.naver.com/lovecrescent", "intro": "매일의 일상에 반짝임을 더해요 ໒꒱˚⁎⁺˳"}, "G52": {"instagram": "https://www.instagram.com/love_polaris_?igsh=eGIxbmpscTg5Nm43&utm_source=qr", "website": "https://grafolio.ogq.me/profile/러브폴라리스/profile", "intro": "귀빨간 사막여우 여니와 선인장도마뱀 쩨쩨를 그리는 작가 러브폴라리스입니다! \n나만의 별을 찾는 당신의 여정을 응원하고 함께 위로할게요."}, "G30": {"instagram": "https://www.instagram.com/roughhands_illust?igsh=YzJ3OHo4MmtvY3U5&utm_source=qr", "intro": "강한 블랙과 선을 사용하여, 개성있는 작업을 하고 있습니다"}, "Q46": {"instagram": "https://www.instagram.com/redearsclub/", "website": "https://soshyety.imweb.me/", "intro": "내향인의 사회생활을 응원하는 레드이어스클럽입니다.\n사회생활에서 귀가 빨개지는 순간에 공감하고\n위로와 응원의 메세지를 전합니다!\n\n'LET IT SHY!' 귀가 빨개져도 괜찮아요!"}, "I22": {"intro": "일기는 나에게 보내는 편지 아닐까요?\n레터투러브는 일상의 순간을 편지처럼 담아내고,\n사랑을 써 내려가는 문구 브랜드입니다."}, "J13": {"instagram": "www.instagram.com/relish_life", "intro": "일러스트레이터 렐리시입니다. 일상에서 포착한 장면과 고유한 분위기를 그림, 단행본, 매거진, 다양한 제품에 담습니다. 사소한 흔적과 공감을 모티브로 한 작업들이 여러분께 다정한 날"}, "M14": {"instagram": "https://www.instagram.com/rosemellyclub?igsh=ZDg1ZTdoaHJ2emg0&utm_source=qr", "intro": "장미의 가시를 사랑하는 멜리의 세계 𓈒𓏸 𓂂𓈒　𓂂 𓈒𓏸𓂃 𓈒 𓂂𓏸\n꿈꾸는 소녀들과 꿈 속 작고 부드러운 요정들의 이야기를 들려드릴게요"}, "M27": {"instagram": "https://www.instagram.com/rottencandle.x_x/", "website": "https://x.com/saltyy666", "intro": "세상의 이레귤러들이 모이는 곳, 로튼캔들입니다."}, "L22": {"website": "https://lohaillust.com/", "intro": "기억과 이야기를 담은 일러스트를 그립니다"}, "H29": {"instagram": "www.instagram.com/lucyday0311", "intro": "청춘의 빛나는 순간을 따뜻하고 사랑스런 느낌으로 그리는 일러스트작가 루시입니다."}, "D33": {"instagram": "https://www.instagram.com/lufishstudio/", "intro": "동물과 고양이, 자연을 주로 그립니다. 일러스트와 함께 일러스트북과 그림책, 팝업북 등의 독립 출판도 진행하고 있으며, 문구 제품도 제작하는 등 다양한 작업들을 하고 있습니다."}, "G13": {"instagram": "https://www.instagram.com/illustrator_r.u.h.a", "website": "https://www.youtube.com/channel/UCAPDCpFGJuiNehMgf2CshUw", "intro": "🌸 자연과 사람의 따뜻한 감성 오일파스텔 드로잉\n🎨루하르모네 화실 운영 @ruha_remone"}, "D32": {"instagram": "https://www.instagram.com/rsseau_", "intro": "가장 작고 몽글한 이야기를 그려요.\n당연하다고 느끼는 일상 속 소소한 기억의 감정들을 다시 되짚어 봅시다"}, "O49": {"instagram": "www.instagram.com/rikki_3778", "intro": "리끼와 다양한 친구들의 특별한 것이 아닌 소소한 일상과 상상으로 저뿐 아니라 봐주시는 분이 조금이나마 쉬어가길 바라는 마음을 가득 담아 작업하고 있습니다."}, "R34": {"instagram": "https://www.instagram.com/rrpp_friends/", "website": "riripipi.com"}, "O09": {"instagram": "https://www.instagram.com/libet_hs/", "intro": "안녕하세요 리벳입니다"}, "T15": {"instagram": "https://www.instagram.com/living_n_life", "website": "https://livingandlife.co.kr", "intro": "국내 니트 조직 공장을 운영하고 있는 \"리빙앤라이프\" 입니다.\nAI/JPG/PNG 등 디자인 시안으로 고급스러운 자카드 직조 니트 완제품 굿즈를 제작해 드립니다."}, "R03": {"instagram": "https://www.instagram.com/art_re.j?igsh=MTVqbTZlaDdnZnNwcg%3D%3D&utm_source=qr", "intro": "감정을 이야기 합니다.\n음악을 통한 감정, 일상의 마음을 그림으로 기록하고\n감정카드인 “님프카드“로 위로의 마음을 선물합니다.\n아이패드 디지털 드로잉과 한국화 물감으로 작업합니다."}, "G04": {"instagram": "https://www.instagram.com/licar_g/", "website": "https://licar.creatorlink.net/", "intro": "cat! cat! cat!"}, "S07": {"instagram": "www.instagram.com/recorder_fac", "website": "www.recorder-fac.com", "intro": "일상에 귀여운 에너지를 주는 캐릭터 기반의\n디자인 브랜드 리코더팩토리 입니다"}, "D08": {"instagram": "https://www.instagram.com/littletinyroom", "website": "https://littletinyroom.creatorlink.net/", "intro": "illustrator / character designer\n\n리틀타이니룸을 운영하고 있는 일러스트레이터 아쿠입니다."}, "B25": {"instagram": "https://www.instagram.com/hajimagomin/", "intro": "함께 해요, 스티커로 채우는 기록들"}, "K46": {"instagram": "https://www.instagram.com/mariuniverse.book/"}, "Q09": {"instagram": "https://www.instagram.com/arum2222/", "website": "https://smartstore.naver.com/marine_snow", "intro": "소소한 일상에 고양이 한 스푼을 더해 달콤한 일상을 만들어갑니다.\n고양이를 모티브로 공예, 일러스트, 디자인 문구등을 작업하고 있습니다."}, "O37": {"instagram": "https://www.instagram.com/dalp_01/", "intro": "마법사고양상점은 햄스터가 되고싶었던 마법사 ’고양‘이 함께 살고있는 햄찌들과의 시간을 일러스트로 담아내는 상점입니다. 일러스트를 활용해 주로 팬시 스티커를 제작하고 있습니다."}, "B05": {"instagram": "https://www.instagram.com/marsh__land/", "intro": "마시랜드 & 큐트버스 입니다."}, "R33": {"instagram": "www.instagram.com/my_grimmi", "website": "mygrimmi.com", "intro": "\"Dream Together, Smile Forever\"\n\n토실토실 오또와 마이그리미 친구들의 귀여운 모험에 초대합니다!"}, "Q23": {"instagram": "https://www.instagram.com/maimoi_y/?hl=ko", "website": "https://x.com/maimoi_y", "intro": "다정한 순간을 그려요"}, "H11": {"website": "www.mycasualday.com", "intro": "my casual day\n평범한 일상 속 특별한 순간들을 \n담백하고 따뜻한 감성으로 담아냅니다."}, "K49": {"instagram": "https://www.instagram.com/mahastation/", "intro": "전통과 현대를 어우르는 감성 그림을 그립니다."}, "P14": {"instagram": "https://www.instagram.com/mouse_hhead/?hl=ko", "intro": "기계와 영혼이 만나는 새로운 세계를 탐구합니다.\n\nNEW WAVE FOR MACHINE MIND"}, "P46": {"instagram": "https://www.instagram.com/malang_.store/", "intro": "말랑 포근한 친구들이 운영하는 말랑 스토어에 어서오세요! 🤍✨ 따듯한 힐링을 가득 전달해드립니다.🐰🤍"}, "R20": {"instagram": "https://www.instagram.com/mallangxttunttun/", "intro": "마시멜로를 닮은 뚠냥이와 라뚠이, 복슬복슬한 마법사의 바보같은 일상!"}, "V34": {"website": "https://mellowmind.co.kr/", "intro": "말랑한 마음은 심리 전문가들이 만든 마음돌봄 브랜드입니다. 어렵게만 느껴졌던 마음돌봄을 쉽고 즐거운 일상 속 경험으로 만듭니다."}, "G49": {"instagram": "https://www.instagram.com/____mamma", "website": "https://mamma.myportfolio.com/", "intro": "네모네모 세상"}, "V31": {"instagram": "https://www.instagram.com/mangwoncolor/", "website": "https://smartstore.naver.com/mangwoncolor_", "intro": "우리의 그림 생활을 쉽고 즐겁게! 망원칼라는 미술작가이자 망원동에 사는 엄마와 딸, 두 사람이 만드는 수제 수채화 물감 브랜드입니다."}, "C36": {"instagram": "https://www.instagram.com/yifuu.0u/", "website": "https://smartstore.naver.com/yifuu0u", "intro": "⊹ 이푸 작가 | ʏɪғᴜ ⊹\nᯓ★ 맹수만 판매합니다 ˙Ⱉ˙ ₊˚.\n🗯️ 𝘆𝗶𝗳𝘂𝘂𝘃𝘃@𝗴𝗺𝗮𝗶𝗹.𝗰𝗼𝗺"}, "P07": {"instagram": "https://www.instagram.com/__bakery00/", "website": "https://x.com/Bakery00", "intro": "다채로운 색채의 한국풍 일러스트 인물을 그립니다. 시선을 끄는 잘생긴 선비, 귀여운 양반고양이 등, 고전적 세계를 현대적인 색채에 맞춰 CG, 수작업을 넘나들며 그리고 있습니다."}, "U07": {"website": "https://itsmadeby.kr/", "intro": "일상 속 작은 예술을 만나는 문구 편집샵 메이드바이(made by)입니다."}, "N38": {"instagram": "https://www.instagram.com/made_by_yoong", "intro": "애착 인형에서 시작된 \n베개 캐릭터 <라피> 와 \n베개 솜 캐릭터 <쏘미> 는 \n우리들의 소소한 일상을 담아내고 있습니다."}, "K20": {"instagram": "https://www.instagram.com/__maybean/", "intro": "하루를 바꾸는 작은 귀여움 /ᐠ. .ᐟ\\ ★彡\n작은 여우 두 마리, 키위새, 그리고 기분에 따라 색이 변하는 곰돌이까지!\n메이빈 친구들과 함께 소소한 일상에 귀여움을 더해봐요"}, "J27": {"instagram": "www.instagram.com/mogrilka"}, "C05": {"instagram": "https://www.instagram.com/modabi_sea/", "website": "https://t.co/E0HHXLAmp3", "intro": "바다와 해양생물을 좋아해,모다비만의 감성으로 관찰하고 그려내어 문구를 만듭니다.🌊🐬🐠\nⓒMODABI. All rights reserved."}, "F35": {"instagram": "https://www.instagram.com/modori_studio__/", "intro": "-잉키가 보고싶다면 여기로\n-서일페 꼭 들려야할 부스\n-modori studio-"}, "B32": {"instagram": "instagram.com/molee_heeni"}, "F20": {"instagram": "https://www.instagram.com/momoi_round", "intro": "일상에 상상을 더해 그리고 담는 모모이라운드 입니다.\n독립서적과 동화책 작업도 함께 하고있어요."}, "K27": {"website": "link.inpock.co.kr/moseori", "intro": "모서리 스튜디오 ฅ(•̀ 𖥦 •́ ฅ)"}, "S31": {"website": "https://moafesta.com/", "intro": "모아페스타는 캐릭터·일러스트·웹툰 크리에이터와 팬을 연결하고, 응원과 후원으로 IP 성장과 수익화를 지원하는 플랫폼입니다."}, "T07": {"instagram": "https://www.instagram.com/hey.moji/", "website": "https://www.mirae-n.com/main/mn-main-01.frm", "intro": "다섯 친구들의 미치게 귀여운 일상🐰🧦🐶🐯🌱⌒☆"}, "R31": {"website": "https://mhom-ent.kr", "intro": "당신의 일상에 표정을 더합니다."}, "E27": {"instagram": "https://www.instagram.com/mongmong_space/", "website": "https://x.com/mongmong_space", "intro": "꿈 이야기 속 쉬어갈 수 있는 포근한 공간을 표현하는 작가, 꿈꾸는 상점 몽몽스베쮸입니다."}, "L18": {"instagram": "https://www.instagram.com/mongjin_art/", "website": "https://smartstore.naver.com/mongjin_art", "intro": "맛있는 음식과 즐거운 일상을 그리는 몽진아트입니다💕"}, "I28": {"instagram": "https://www.instagram.com/mio_jae/", "intro": "고양이와 우리의 전통문화가 만나는 곳, 콘텐츠 스튜디오 묘재입니다.\n일러스트레이션과 라이프 굿즈를 통해 일상 속 작은 즐거움과 따뜻한 감성을 전합니다."}, "A18": {"instagram": "https://www.instagram.com/silverjakka_emot/?hl=ko", "website": "https://x.com/munyong0fficial", "intro": "달나라에서 온 떡토끼 무뇽이와 꿀떡이들💖\n지구에서 만난 칭구들과 함께 행복을 전하고 싶어요🥰"}, "H21": {"instagram": "https://www.instagram.com/ki_rin_/", "website": "https://inabooth.io/ko/ip/INB-HO-WYPQ", "intro": "🦒 가장 나다운 무늬를 찾아가는 중"}, "L41": {"instagram": "instagram.com/mood_wash", "intro": "1x1=MoodwasH"}, "F13": {"instagram": "https://www.instagram.com/mouun._.factory/?hl=ko", "intro": "일상의 따뜻한 순간에 재미난 상상력을 더해 그립니다."}, "M33": {"website": "https://www.logonmucuzi.com/", "intro": "프리랜서 캐릭터 디자이너 / 일러스트레이터 MUCUZI입니다.\ncontact : rkdud0207@naver.com"}, "Q32": {"instagram": "https://www.instagram.com/fig080", "intro": "사이버 세상에서 겪는 이야기"}, "F37": {"instagram": "www.instagram.com/lemonlunalove", "website": "https://eternaljourney.ananti.kr/brand/0368", "intro": "자연주의 동화감성. 천진난만한 동물과 신비로운 대자연을 소재로 일상을 동화적 상상력으로 재해석합니다. 대자연의 밝은 에너지를 작품을 통해 전하고자 합니다."}, "R12": {"instagram": "https://www.instagram.com/mooon__ni/", "intro": "안녕하세요 일러스트 작가 문니입니다."}, "T24": {"website": "https://www.thepinkfongcompany.com/", "intro": "<문샤크:아이돌피스>💜\n내 이야기가 궁금하다면?\n⬇️ 링크로 들어와 줘! ⬇️\nhttps://www.instagram.com/moonshark_official/"}, "O45": {"instagram": "https://www.instagram.com/mukumukudang/", "website": "https://smartstore.naver.com/radah_", "intro": "멍실몽실, 포근포근한 의미를 가지고 있는 ”므끄므끄\"는 높은 하늘, 커다란 구름에서 미끄~러져 떨어진 잔망스런 구름조각을 말합니다."}, "I39": {"instagram": "https://www.instagram.com/rakrak.min/", "website": "https://smartstore.naver.com/mynartstore", "intro": "숲의 초록, 쉼과 회복의 색. 자연의 생명력과 순환의 흐름을 초록 식물에 담고, 나쁜 기운을 막아주는 벽사의 의미를 담은 민화 속 호랑이를 함께 어우러지게 작업 합니다."}, "F32": {"instagram": "https://www.instagram.com/mio.soop", "intro": "마음 속 숨겨둔 하나의 동화를 꺼내 읽어주세요𓅯"}, "Q34": {"instagram": "https://www.instagram.com/uglypig_1/", "intro": "어린 시절의 추억을 그림으로 그리는 미운돼지입니다!"}, "H34": {"instagram": "https://www.instagram.com/mii_e2", "website": "https://litt.ly/mii222eee", "intro": "햇살처럼 다정한 순간을 그리고, 작은 빛과 이야기를 전합니다. 네이버 웹툰에서 <짝사랑 마들렌>을 연재했습니다."}, "N50": {"instagram": "https://www.instagram.com/mizzi._.luv/", "intro": "우리의 일상을 귀엽게 담아냅니다.\n\n미찌도록 귀여운\n 아기 강아지 몽찌 & 아기 토끼 토찌의 일상"}, "T18": {"instagram": "https://www.instagram.com/mitory_official/", "website": "https://bytori.co.kr/goods/goods_list.php?cateCd=022", "intro": "기어가도 괜찮아 〰️〰️\n제대로만 가고 있으면"}, "N41": {"website": "mindobitto.com", "intro": "상상하는 이미지들을 손끝으로 표현합니다."}, "M38": {"instagram": "https://www.instagram.com/jaehoimin/", "intro": "고양이를 모티프로 이상하고 재미난 글과 그림, 물건을 만듭니다."}, "O53": {"instagram": "https://www.instagram.com/minki_oo", "intro": "𝐀𝐥𝐥 𝐚𝐫𝐞 𝐰𝐞𝐥𝐜𝐨𝐦𝐞!\n그림책 작가 민키입니다. 펜과 종이를 이용해 복작복작 다양한 사물과 캐릭터들이 함께하는 즐거운 공간을 그립니다 ♪"}, "K45": {"instagram": "https://www.instagram.com/mill_illust/", "intro": "밀!"}, "I52": {"instagram": "https://www.instagram.com/mildybk/", "website": "https://smartstore.naver.com/mildyblack", "intro": "흑백 세상 속 온화함과 반짝임"}, "O27": {"instagram": "https://www.instagram.com/mings_box", "intro": "밍다람그림일기는 2030 직장인과 일상에 지친 이들을 위한 공감 캐릭터 브랜드입니다.\n\n유쾌하고 병맛스러운 일상툰과 굿즈로 웃음과 위로를 전합니다."}, "C10": {"instagram": "www.instagram.com/mingming.lemon", "website": "https://smartstore.naver.com/mingminglemon", "intro": "‘재밌는 일상, 언제나 함께 하고픈 나의 반려 친구’\n \n저는 주변의 동물과 사물들 모두에 이야기와 색감을 불어넣어 나만의 일상을 담아내는 그림작가 ‘밍밍레몬’ 입니다."}, "Q39": {"instagram": "https://www.instagram.com/baguet__te/", "intro": "파리에서 영감을 받아 일상을 따뜻하고 위트 있게 그립니다. 9년의 브랜드 디자인 경력을 더해, 지금은 ‘바게트효’만의 시선으로 일상을 특별한 장면으로 재해석하는 일러스트레이터입니다"}, "D01": {"website": "linktr.ee/barengrim", "intro": "얇고 가벼운 것들이 모여 만들어지는, 결코 가볍지 않은 무게에 대해 이야기합니다. 일상 속에서 마주하는 것들을 하나의 결로 엮어나가는 작업을 하고 있습니다."}, "F02": {"instagram": "https://www.instagram.com/ramrammy.store/", "intro": "바부감쟈와 다른 하찮은 칭구들이 모인 람람한 잡화점을 운영중인 작가, 람입니다."}, "C38": {"website": "http://Instagram.com/parknyam", "intro": "일러스트레이터 박냠입니다"}, "J24": {"instagram": "https://www.instagram.com/minjooparkart", "website": "https://blog.naver.com/minjooparkart", "intro": "색연필의 부드러운 질감과 도자기의 단단한 물성으로 따뜻한 일상을 기록합니다."}, "F09": {"website": "https://www.parksunjoo.com/", "intro": "계절의 변화를 그리며 내면의 성장을 기록하는 작가\nPainting / Illustration"}, "R48": {"instagram": "https://www.instagram.com/ssobagi/", "intro": "소소한 만화, 소박한 그림, 소중하지 않은 순간들을 그립니다."}, "N43": {"instagram": "instagram.com/curly___curly", "intro": "소녀들의 하루를 그려요."}, "T34": {"instagram": "https://www.instagram.com/vanwalk.korea/", "website": "https://www.vanwalk.co.kr/", "intro": "All things Joyous! We are VANWALK"}, "G05": {"instagram": "https://www.instagram.com/bammansim?igsh=Z25ucXcyNmVvcnE0&utm_source=qr", "website": "https://smartstore.naver.com/bammansim"}, "J10": {"instagram": "https://www.instagram.com/studio_soolm/", "website": "https://kr.pinterest.com/studio_soolm/", "intro": "밥솥에서 쫓겨난 밥덩이"}, "H14": {"instagram": "https://www.instagram.com/bae.jye/", "website": "https://3b.myportfolio.com/", "intro": "bae.jye\n평범한 일상을 관찰하며 마음에 남는 장면들을 기록합니다."}, "R05": {"instagram": "instagram.com/bae_cci1209", "intro": "여름과 알로하 셔츠를 좋아하는 사람입니다."}, "H52": {"instagram": "https://www.instagram.com/irenepaeart/", "website": "https://irenepae.com/", "intro": "일상에서 자세히 보지 않으면 지나쳐 버릴 작은 순간들부터 우리의 상상 속 깊은 곳에 숨어 있는 이야기들까지, 다양한 이야기들을 따뜻하고 다정한 시선으로 그려내고 있는 일러스트레이터"}, "B24": {"instagram": "https://www.instagram.com/no_197_/", "intro": "@no_197_"}, "E23": {"instagram": "https://www.instagram.com/team.baeksan/", "intro": "."}, "D07": {"instagram": "https://www.instagram.com/baek_sanga?igsh=MTV4aGVlaHllZXhiaw==", "website": "https://x.com/Baek_SangA?t=aJrziPX_9SumwFds2QppEQ&s=09", "intro": "고딕스러운 그림에 반짝임을 담아 그려나가는 백상아입니다.\n동물신사들의 이야기를 주로 풀어서 그려나가고 있어요. 하나의 판타지 세상에서 벌어지는 이야기들을 들어보세요."}, "I09": {"instagram": "https://www.instagram.com/jheeart", "intro": "일상의 소중한 것을 발견하고 창작그림책/페인팅 작업을 하고 있는 재희입니다."}, "R24": {"instagram": "https://www.instagram.com/burkoolee", "intro": "나의 애완식물 \"왕파 랑 나파\"\n\n베란다 텃밭에서 살면서 우리의 무료한 일상에 작은 웃음을 주는 \n하찮고 잔망스런 친구들"}, "K30": {"instagram": "https://www.instagram.com/kimso.records", "intro": "일상과 마음속 작은 세계를 그리는 김소은입니다."}, "E07": {"website": "https://veryberrybap.com/", "intro": "C40놀러오세요!"}, "C08": {"instagram": "www.instagram.com/bebez_z", "intro": "차분하고 귀여운 그림을 그리는 베베입니다."}, "A23": {"instagram": "https://www.instagram.com/beloiro", "intro": "멸종위기동물들을 모티브로 캐릭터작업을 하고 있어요.\n벨로이루만의  감성이 담긴 귀여운 아트토이를 통해 지친 일상에 작은 행복과 힐링이 되기를 바랍니다."}, "O16": {"instagram": "https://www.instagram.com/byeol_geung/", "website": "https://mkt.shopping.naver.com/link/681ce18ffd7d167e0feab852", "intro": "별긍상점은 귀엽고 사랑스러운 토곰이, 애착인형 곰돌이, 반려묘 긍냥이가 많은 사람들과 행복을 나누기 위해 운영 하는 따뜻한 상점입니다."}, "K15": {"instagram": "https://www.instagram.com/dal_gomm2/", "website": "https://blog.naver.com/dal_gomm2", "intro": "보름달곰즈 친구들과 함께 푸른별 여행해요 !"}, "I40": {"instagram": "https://www.instagram.com/boricha.room", "intro": "사람들을 방에 초대해 구수한 보리차 한 잔 나누듯, 따뜻하고 편안한 일상의 순간들을 그림으로 담아냅니다. 일러스트와 회화, 드로잉 기반으로 작업을 이어가고 있습니다."}, "F25": {"instagram": "instagram.com/bluemanatee", "website": "bo-yoon.com", "intro": "감정의 억압과 통제를 상징하는 '감정 보따리'와 '뜨개옷을 입은 사람'등, 반복되는 모티프를 통해 정체성 혼란 및 다양한 고민과 불안을 형상화한 '마음의 방'을 만들고 있습니다."}, "O22": {"instagram": "https://www.instagram.com/boy.meets.girl_", "intro": "사람-사물-풍경 다양한 만남에서 낭만을 찾아\n그림과 애니메이션으로 표현합니다."}, "N34": {"instagram": "https://www.instagram.com/bokchee_art_/", "website": "https://bokcheepf.myportfolio.com/", "intro": "따뜻함을 담은 한조각을 그립니다🌷"}, "O21": {"instagram": "www.instagram.com/bomnaenge"}, "O46": {"website": "https://bio.link/popbanao", "intro": "한국의 아름다운 전통 문양과 소품들을 새로운 방식으로 재해석하며 몽환적인 색감을 연구합니다.\n자수 티백 시리즈를 꾸준히 제작중이에요."}, "K23": {"instagram": "https://www.instagram.com/bong_bong_illust/?igsh=Y2tvYTl1aThsMWYz&utm_source=qr#", "intro": "\"항상 나무 같은 그림을 그리고 싶었어요.\n지친 하루에 잠시 머무를 수 있는 그림,\n그 속에서 작은 쉼이나 설렘을 느끼길 바라요.\""}, "K25": {"instagram": "https://www.instagram.com/bongja_.illura?igsh=ZHhmOTdtZDduNDA5&utm_source=qr", "intro": "스토리가 담긴 판타지 친구들을 그려요(*´꒳`*)"}, "N48": {"instagram": "https://www.instagram.com/bookie_diary/", "intro": "다꾸러의 일상을 그리는 인스타툰작가 부키입니다. \n\n나를 알기 위해 방황하고, 시행착오를 겪는 과정을 기록하며\n툰으로 공유하여 나와 같이 방황하는 칭구들에게 도움과 용기를 줍니다!"}, "K53": {"instagram": "https://www.instagram.com/baksaesama_", "intro": "즐겁게 그립니다"}, "Q24": {"instagram": "https://www.instagram.com/blackletter_kr/", "intro": "블랙컬러를 베이스로 디자인 문구류, 굿즈를 제작합니다."}, "L25": {"instagram": "https://www.instagram.com/limyesool/", "website": "https://smartstore.naver.com/blackjellyclub", "intro": "안녕하세요.\n꿈과 상상, 휴식을 전하는 블랙젤리클럽 입니다."}, "G09": {"instagram": "www.instagram.com/blackpencilclub_rae", "intro": "*흑백의 세계에서 다채로운 인물들을 그립니다. \nSuit, Fashion, Croquis"}, "N36": {"instagram": "https://www.instagram.com/nayoonsung/", "website": "https://smartstore.naver.com/blankcat", "intro": "be anything, fill the blank!\n무엇으로든 채울 수 있는 비어있는 고양이 블랭크캣과 소녀의 친밀한 교감을 그립니다."}, "F16": {"website": "soonsim.co.kr", "intro": "오일파스텔로 그리는 따뜻한 일상"}, "V46": {"instagram": "https://www.instagram.com/bibi1004/", "intro": "캐릭터 일러스트"}, "C02": {"instagram": "https://www.instagram.com/bee.arc.hive/", "website": "https://bee-arc-hive.com/", "intro": "작은 벌이 차곡차곡 쌓아올린 벌집의 기록 속, \n디자이너가 그리고 만드는 세라믹 브랜드입니다."}, "H12": {"website": "https://x.com/beeya_ouo", "intro": "버섯이 되지 못한 포자와 작은 동물 친구들을 그리고 있어요"}, "U15": {"instagram": "https://www.instagram.com/biyaluv_me/", "website": "https://www.biyacraft.com", "intro": "비야크라프트입니다."}, "C35": {"instagram": "https://www.instagram.com/bf_ok", "intro": "소녀들의 일상과 사계절을 그립니다."}, "E24": {"instagram": "https://www.instagram.com/visualstoryteller", "website": "www.visteller.com", "intro": "역사를 그림으로 말하다. 한 장으로 보는 역사 시리즈, VISUALSTORYTELLER."}, "U35": {"website": "https://bfashion.me/", "intro": "패션 기업/디자이너가 크리에이터들과 서로 소통하고 협업할 수 있는 디지털 공간으로, 콘텐츠와 아이디어를 융합하여 트렌디한 제품을 창작하는 패션 크리에이터 협업 플랫폼입니다."}, "U06": {"instagram": "https://www.instagram.com/b.fter/", "website": "https://smartstore.naver.com/bfter", "intro": "비프터는 색과 향으로 즐거움을 더하는 아트 브랜드입니다. 창작자들에게 새로운 영감을 전하고,\n사용하는 순간에 즐거운 경험을 선사하며 일상의 창작을 더욱 특별하게 만들어갑니다."}, "L34": {"instagram": "https://www.instagram.com/bigbigcatkr/", "website": "https://bigbigcat.kr/", "intro": "요가 수련과 일상의 감정을 ‘빅빅캣’이라는 고양이 캐릭터로 풀어내는 일러스트 기반 브랜드입니다."}, "G48": {"instagram": "https://www.instagram.com/papeterie.atelier/", "website": "https://cara.app/papeeterie", "intro": "'귀여운 것들이 내 세상을 구한다'\n귀여운 것들이 일상 속에 녹아들어 행복을 가져다주고, 그것들로 인해 내가 좋아하는 것을 잊지 않도록 하는 것을 추구합니다 :)"}, "G34": {"website": "instargram.com/jellygomz", "intro": "당신의 마음도 뽀송하게!\n뽀송 먼지뭉치와 함께 해요♥"}, "C03": {"instagram": "https://www.instagram.com/ppomppom_studio/", "website": "https://ppomppom-studio.com/", "intro": "일상의 깜찍함을 담아 그리고 만들어요"}, "E28": {"instagram": "https://www.instagram.com/petitfactory_official/", "website": "www.petitfactory.net"}, "P21": {"instagram": "https://www.instagram.com/engisstuff/", "intro": "커피와 고양이를 그립니다.\n주로 리소인쇄를 합니다."}, "I32": {"instagram": "https://www.instagram.com/sarissa_art00136/", "website": "https://www.youtube.com/sarissa_art", "intro": "SARISSA 사리사\n\nSouth Korean illustrator. Drawing retro girls from Hong Kong and the Pacific\n홍콩,하와이,레트로"}, "I16": {"instagram": "https://www.instagram.com/sa_seo_/#", "website": "https://x.com/sa_seo_", "intro": "저는 어둠 속에서 빛나는 자개를 수놓아, 책장을 만드는 작가 \n사서(SASEO)입니다."}, "K47": {"instagram": "https://www.instagram.com/i_o.saso/", "intro": "좋아하는 것으로 나를 채우듯, 그림으로 누군가의 하루를 채울 수 있기를 바랍니다."}, "G50": {"instagram": "https://www.instagram.com/april_eleven_youyeong", "intro": "우리는 유영하고 있는 삶을 살고 있습니다.\n물속 또는 젖어 있는 모습을 음악적 영감을 통해 인물울 탄생시키고 있습니다."}, "F24": {"instagram": "https://www.instagram.com/sai.sae.sai/", "intro": "새를 좋아해서 그의 이름을 풀어 쓰고 있습니다.\n가장 애정하는 새와 오랫동안 함께한 반려묘, 그리고 창밖에 보이는 모든 자연을 담아 브랜드 '사이새사이'로 전개해 나가고 있습니다."}, "A16": {"instagram": "www.instagram.com/psyf_official", "intro": "PSYF는 엉뚱하고 유쾌한 일러스트레이션과 그래픽을 기반으로 고유한 캐릭터와 세계관을 만들어가는 아트워크 브랜드입니다."}, "D17": {"website": "https://linktr.ee/__san99__", "intro": "펜과 수채화를 활용해 조용하고 동화같은 그림을 그립니다."}, "H39": {"instagram": "https://www.instagram.com/salposi.illust", "intro": "행복은 찰나에 가깝고 그마저도 쉬이 찾기 어려워서\n따뜻한 빵, 복슬복슬한 강아지처럼 따듯함을 주는 것들을 그리고 만들어 곁에 두며 작은 행복들을 찾습니다"}, "P49": {"instagram": "https://www.instagram.com/shashamiu/"}, "I45": {"instagram": "https://www.instagram.com/shalomu_art/", "intro": "🇨🇳🇭🇰🇲🇴🇹🇼🇷🇺🇪🇸🇵🇹🇬🇧🇫🇷🇩🇪🇨🇿🇦🇹🇭🇺🇮🇹🇺🇸\n여행하듯 살아가는 일상을 글, 그림으로 기억하고 추억합니다 : )"}, "H23": {"instagram": "https://www.instagram.com/seonak_?igsh=NnBzZXltcDR6djdl", "intro": "안녕하세요. 소녀를 그리고 있는 서낙입니다."}, "L20": {"instagram": "https://www.instagram.com/seoro__d", "intro": "세심한 펜 드로잉을 통해 표현한 다양한 건물, 인물의 모음집입니다. 드로잉을 통해 추억을 기록합니다."}, "G29": {"instagram": "https://www.instagram.com/its.ssung/", "website": "https://litt.ly/seo.sung?fbclid=PAZXh0bgNhZW0CMTEAAafZpGhMXiOWMtULfYIs4-p2Gc1ijPfO2-ZE9IIh-IoMxxUy-F0TFMIttVdpIA_aem_wLC1mLPI3eIufTDzu2kojQ", "intro": "반짝이는 취향과 오브젝트를 프레임 담는 ‘서성seosung’입니다\n\n<미묘소녀> 시리즈는 \n6명의 소녀들의 오브젝트와 취향을 담아 순정만화의 설레임과 마법소녀의 반짝임을 보여줍니다"}, "U33": {"instagram": "https://www.instagram.com/sia_visual_design/", "website": "https://www.seoularts.ac.kr/web/main/mainPage.do", "intro": "서울예술대학교 디자인학부 시각디자인전공\nTRACE WALL : Wardrobe Of Images"}, "A13": {"instagram": "https://www.instagram.com/3eotty?igsh=dzdkdGt2cnV3Njd6&utm_source=qr", "website": "https://x.com/3eotty?s=21", "intro": "안녕하세요 ! 서티입니다"}, "G17": {"instagram": "https://www.instagram.com/sunw_drawing?igsh=MXFnZmRiOHR5cjJtMg%3D%3D&utm_source=qr", "intro": "일상의 틈에서 피어난 이야기를 그립니다."}, "N40": {"instagram": "https://www.instagram.com/seongki_b/", "website": "https://seongki.kr/", "intro": "︵\n𝘞𝘰𝘳𝘬 𝘣𝘢𝘴𝘦𝘥 𝘪𝘯 𝘴𝘦𝘰𝘶𝘭\n𝘐𝘭𝘭𝘶𝘴𝘵𝘳𝘢𝘵𝘪𝘰𝘯 · 𝘋𝘦𝘴𝘪𝘨𝘯 · 𝘈𝘯𝘪𝘮𝘢𝘵𝘪𝘰𝘯"}, "C27": {"instagram": "https://www.instagram.com/omil_zomil/", "intro": "냉장고에서 살고있는 도자기 곰\n\n맛있는 음식으로 귀여운 행복을 전해요◟̆◞̆"}, "S25": {"instagram": "https://instagram.com/second_morning", "website": "secondmorning.co.kr", "intro": "두 번째 맞이하는 아침과 같이 일상 속 스며들어있는 소소한 행복과 여유로움을 추구합니다.\n단순한 것에도 행복한 세모 친구들의 모습을 통해 짧게나마 미소 지을 수 있길 바랍니다."}, "E38": {"website": "charadeshow.com", "intro": "셔레이드쇼는 고양이의 무료한 일상 뒤 숨겨진 모험을 상상합니다.\n마치 어느 밤 지구를 구하거나 악당의 침공을 막아낸 영웅 이야기처럼요!"}, "M37": {"instagram": "instagram.com/sonu_choi_", "intro": "일러스트레이터 소누입니다.\n평범한 일상의 반짝이는 순간과 감정들을 기록합니다."}, "N05": {"instagram": "https://www.instagram.com/soda_8_8", "intro": "한국적인 무드에 동화적 판타지를 더해 그림을 그리는 일러스트레이터 소다입니다.\n맑고 투명한 색감과 몽환적인 텍스처를 활용하여, 잔잔한 감정과 여운을 담아내는 작업을 하고있습니다."}, "P12": {"instagram": "https://www.instagram.com/so.ror0/", "intro": "모든 하루가 소중하길, 꼬마 유령하루와 친구들을 그립니다.\n\n일상 속 편안함과 사소한 순간들의 소중함을 그림에 담고 있는 소로로입니다 :)"}, "L09": {"instagram": "https://www.instagram.com/so.m.an/", "website": "https://soman-illustrator.com", "intro": "작은 점과 선을 엮어 흑백의 그림을 그리는 일러스트레이터"}, "H41": {"instagram": "https://www.instagram.com/soseol_illust/", "website": "https://soseolillust.imweb.me", "intro": "색연필로 그리는 포근한 일러스트🩵\n\n저의 작은 그림이 작디작은 눈송이가 되어서 \n세상을 조금이라도 따뜻하게 만들 수 있으면 좋겠습니다⸝⸝ ᷇࿀ ᷆⸝⸝"}, "N39": {"instagram": "https://www.instagram.com/sosonut.studio", "intro": "sosonut studio"}, "C28": {"instagram": "https://www.instagram.com/soso.roun", "website": "https://smartstore.naver.com/soso_roun_", "intro": "작고 귀여운 고양이인 뽀양이와 뽀시래기들을 그리는 브랜드 ‘소소로운’입니다."}, "R44": {"instagram": "https://www.instagram.com/page_soso/", "intro": "어떤 그림을 그릴지 고민하는 시간과 낙서 같은 스케치를 즐기며 그림을 그리고 만들어가고 있습니다."}, "L51": {"instagram": "http://instagram.com/softyfog", "intro": "부드러운 안개처럼 따뜻하고 포근한 그림을 그립니다 :)🤍"}, "E21": {"instagram": "https://www.instagram.com/sol_drawing__?igsh=aHB2MTF1d2lueXlr&utm_source=qr", "intro": "오일파스텔로 저만의 소중한 순간을 담아내는 작가 솔그림입니다:)"}, "J34": {"instagram": "https://www.instagram.com/_solion?igsh=d3RyeWlwaGZ3dWxn&utm_source=qr", "intro": "우리의 꿈같은 순간을 그립니다."}, "P09": {"instagram": "https://www.instagram.com/songnyang_ssi", "website": "http://litt.ly/songnyangssi", "intro": "일상에서 수집한 순간을 그리고 패턴을 만들어요.\n동물과 식물을 좋아해요.\n소외받는 것에 눈길이 더 가요."}, "R38": {"instagram": "https://www.instagram.com/soo_doll?igsh=MXhiM3JqbTJ4cDF1eA%3D%3D&utm_source=qr", "intro": "발레와 인어그림을 그리며 최근에는 도자기를 열심히 굽고있는\n일러스트레이터 수라고 합니다."}, "I54": {"instagram": "https://www.instagram.com/soonori_studio", "website": "https://soonoristudio.com/", "intro": "짧은 꼬리를 가진 다람쥐, 노리베어는 스스로를 곰이라 정의했습니다. 노리베어를 통해 ‘나다움’에 대한 이야기를 짓고, 실과 바늘로 그립니다."}, "H47": {"instagram": "https://www.instagram.com/Suda_0107", "intro": "안녕하세요. 햇살같이 따듯한 감성과 다채로운 색감으로 몽환적인 느낌을 전하는 그림 작가 \"수다\"입니다."}, "J06": {"instagram": "https://www.instagram.com/collector_mumu/", "website": "https://www.threads.com/?xmt=AQGzAeOWR4w8yAbEbJyW8PVnqoz6kaQlYZAXLXDrXFTYBiI", "intro": "행복은 자고로 \n든든한 귀여움에서 오는 법..🐹⭐ \n\n나눈ㅇㅑ 행복한 코찔찔이 햄스ㅌㅓ. \n귀여운 햄찌와 작고 소듕한 행복 수집중-!"}, "B09": {"instagram": "https://www.instagram.com/sukeydokey", "intro": "안냐세요~ 쥐순이의 수키도키입니다!"}, "F19": {"instagram": "https://www.instagram.com/soup_effect/", "intro": "일러스트레이터 수프효과입니다."}, "P42": {"instagram": "https://www.instagram.com/soomba_s/", "intro": "안녕하세요 숨만쉬어도 귀여운 숨바의 \n귀엽지만은 않은 일상을 그려내고 있습니다."}, "L36": {"website": "snooze.kr", "intro": "스누즈키튼즈는 캐릭터, 인물, 데코까지\n다꾸러 취향을 가득 담은 문구 브랜드입니다.\n\n(※ 구매증정품은 행사마다 상이하므로 INFO 게시물을 참고해주세요.)"}, "U01": {"website": "https://smartstore.naver.com/stabilo", "intro": "Express yourself with colors! 🎨🌈\n일상에 컬러를 더하다!"}, "P41": {"instagram": "https://www.instagram.com/illust_nimo/", "website": "https://smartstore.naver.com/studionimo", "intro": "고양이를 사랑하는 마음을 담아 그림을 그리는 일러스트 브랜드, '스튜디오 니모'입니다. 저희의 작은 친구들이 전하는 따스하고 귀여운 이야기들로 일상을 가득 채워보세요."}, "H26": {"instagram": "https://www.instagram.com/xoxodingxx", "intro": "☘︎˖ദ്ദി˶⦁⩊⦁)❤︎ ༘⋆ 지친 어른이를 위한 행운 전문가 스튜디오딩스 입니다. ⸌☻ັ⸍꙳"}, "B19": {"instagram": "https://www.instagram.com/studio._.myoni", "website": "https://smartstore.naver.com/studio_myoni", "intro": "⋆˳⋆˳ ˚ ☾ ˚ ˳⋆ ˚☽˚˳ ⋆․ ‧ ˚ *\n안녕하세요 스튜디오 묘니입니다.\n귀여운 캐릭터들을 통해 모든 사람의\n마음에 힘과 위로가 되는 그림을 그립니다."}, "E25": {"instagram": "https://www.instagram.com/studio__bibi/", "website": "https://smartstore.naver.com/studio_bibi", "intro": "따스한 동화 일러스트를 작업하고 있습니다."}, "V43": {"instagram": "https://www.instagram.com/sosohan6611", "website": "https://linkfly.to/50530xCe3VR", "intro": "소소하지만 사랑스러운 인형들을 만드는 소소한 인형공방 입니다"}, "D03": {"instagram": "https://www.instagram.com/studio_arvie/", "intro": "🌙 잠시 쉬어가는 환상, 어둠 속의 빛✨\n🦋 미지 세계의 탐험기록가"}, "M51": {"website": "https://notefolio.net/studio_chongchong", "intro": "이로와 이랑이의 별을 향한 모험\nadventure toward the star"}, "B27": {"instagram": "https://www.instagram.com/studio_fondue/", "website": "https://grafolio.ogq.me/profile/스튜디오퐁듀/project"}, "I01": {"instagram": "https://www.instagram.com/seul.grim", "intro": "일상 속에서 느끼는 작은 감정들과 상상들을 그려요."}, "M06": {"instagram": "www.instagram.com/slowparis_", "website": "https://slowparis.cafe24.com/m/index.html", "intro": "여유로운 파리 일상처럼, 슬로우파리 입니다.\n\n일상에서 마주친 장면을 여유로운 속도로 살아가는 파리 분위기를 담아 그렸습니다."}, "K37": {"instagram": "https://www.instagram.com/seumseum_studio/", "intro": "함께 사는 고양이들로부터 영감과 소재를 얻어 이야기를 쓰고 그림을 그립니다.\n고양이와의 우당탕탕 동거 생활로부터 비롯한 웃픈 경험이 대개의 글과 그림에 코믹하게 반영되어 있습니다."}, "R19": {"instagram": "https://www.instagram.com/_skye_0.0", "intro": "그림을 그리고 이야기를 만듭니다. 근데 주로 책을 곁들인..."}, "R08": {"instagram": "https://www.instagram.com/sinana_grim/", "website": "https://sinana.kr/", "intro": "인물을 중심으로 일상의 순간을 그리는 일러스트레이터 신하나입니다."}, "K04": {"instagram": "https://instagram.com/shibao_", "website": "https://x.com/shibao_2525", "intro": "Shibao explores Hoshi no umi, crafting magical goods and drawing with small shapes."}, "U14": {"instagram": "https://www.instagram.com/beorazi8i8", "intro": "인간과 벌레 그 사이에 있는 버라지의 이야기를 그립니다."}, "E01": {"instagram": "instagram.com/siksikhouse", "website": "bio.siksikhouse.com", "intro": "식식인더하우스\nSIK SIK IN THE HOUSE"}, "M07": {"instagram": "https://www.instagram.com/shinkiru.official/", "website": "https://smartstore.naver.com/sharelovethatsall", "intro": "신기루 같은 모든 사랑을 이야기하고 그립니다.\n우리는 빛났었고, 그 순간을 여전히 사랑하기 때문입니다."}, "N53": {"instagram": "https://www.instagram.com/sabinus_/", "website": "https://www.sabinus.net/", "intro": "일러스트레이터 '싸비노'로 활동하고 있는 정승준입니다."}, "F33": {"instagram": "https://www.instagram.com/sunny.jam_", "intro": "날개 귀를 가진 토끼 쿠잉과 쥐 조이, 개구쟁이 솜덩이들이 함께하는  풍경을 그리고 있습니다."}, "A15": {"website": "bxloxxd.com", "intro": "다꾸러가 만드는 다꾸용 다이어리"}, "E12": {"instagram": "https://www.instagram.com/somethingpleasant/", "website": "www.somethingpleasantstudio.com", "intro": "그림을 그리고 실크스크린 프린팅 기법으로 찍어내는 일러스트레이터이자 판화가로 활동하는 김정화입니다. 2015년에 실크스크린 공방 겸 브랜드, 썸띵 플레젠트 스튜디오를 만들었습니다."}, "L17": {"instagram": "https://www.instagram.com/summernight_12/", "website": "https://x.com/summernight_12_", "intro": "달콤하고 귀여운 것들을 그려요 (ʕ・ω・ʔ)☆(^-ω-^)"}, "P19": {"instagram": "https://www.instagram.com/somecats20/", "website": "www.somecats.co.kr", "intro": "용감한 고양이 히요, 소심한 고양이 거무요, 엉뚱한 고양이 코코와 그들의 자그맣지만 늠름한 새앙쥐씨와 함께 작가의 상상을 그리고 있습니다"}, "H54": {"instagram": "https://www.instagram.com/ssuk_essay_toon/", "website": "https://linktr.ee/ssuk_essay_toon?utm_source=linktree_profile_share&ltsid=b5870d65-361c-4194-a394-b5103c96f1c3", "intro": "일상 속 모순적이고 애매한 감정을 에세이툰으로 표현하는 쑥입니다."}, "S33": {"instagram": "https://www.instagram.com/100design_lab?igsh=Z21jZDJwdTAzYjA5&utm_source=qr", "website": "https://smartstore.naver.com/parangparang"}, "H20": {"instagram": "https://www.instagram.com/adoorgyumdang?igsh=ZG1jbmRqc2t1c3Zt&utm_source=qr"}, "N10": {"instagram": "https://www.instagram.com/ar.nyang/", "intro": "입 안에서 금새 사라지는 달콤함이 아니라\n눈에 머무르고 오래 남는 행복을 그립니다.\n정갈하게 담고\n리본을 묶듯 장식을 더해\n달콤한 기쁨을 전합니다."}, "M20": {"intro": "수채화를 기반으로 차분하고 서정적인 분위기의 인물화를 작업하고 있습니다."}, "H53": {"instagram": "https://www.instagram.com/arisol_sumi5?igsh=amZneHl3Mmh4dW92https://www.instagram.com/arisol_sumi5?igsh=amZneHl3Mmh4dW92", "intro": "안녕하세요! \n튤립 노랑을 주제로\n일상의 따스한 온도를 담아내는\n작가 ARISOL 입니다"}, "A05": {"instagram": "https://www.instagram.com/arismarket_", "website": "https://smartstore.naver.com/arismarket_", "intro": "털모찌는 한국의 가래떡에서 영감을 받아 탄생한 인형으로, 흔들면 털이 부풀어 오르는 구조를 통해 한국 문화를 귀엽게 알리고 일상의 스트레스를 자연스럽게 해소할 수 있는 캐릭터 굿즈"}, "I10": {"instagram": "https://www.instagram.com/_ariworks/", "website": "https://smartstore.naver.com/ariworks", "intro": "아기구미호 '메구'의 인간세계 여행일기!\n메구와 함께 오늘의 일기를 만들어보아요:)"}, "M10": {"instagram": "https://www.instagram.com/abarrotes_b_/", "website": "https://smartstore.naver.com/abarrotesb", "intro": "멕시코&중남미 상점! 아바로떼스베"}, "F12": {"website": "Instagram.com/avec_dieu", "intro": "따뜻한 시선으로 일상을 그립니다"}, "I25": {"website": "avofriends.com", "intro": "과일과 채소 캐릭터로 밝은 에너지를 전달하는 [아보프렌즈]\n우리집 주인은 나야! 호빵이! 귀여운 반려견 [호빵아지]\n\n두 캐릭터로 작품활동을 하고 있는 캐릭터 작가 효샤입니다."}, "J54": {"instagram": "https://www.instagram.com/aan_illust?igsh=a3lldnE0Z2h3cGoy&utm_source=qr", "intro": "안녕하세요. 아름다운 평안함을 그리는 작가, 아안입니다.\n계절마다 매력을 담은 풍경과 사람,동물,음식 등의 따스한 소재를 위주로 공감과 위로를 주는 그림을 그리고 있어요."}, "B28": {"instagram": "https://www.instagram.com/ourlooky"}, "D23": {"website": "https://linktr.ee/iren_lovel", "intro": "일러스트레이터 iren/あいれん\nContact : iren_lovel@naver.com"}, "F36": {"instagram": "https://www.instagram.com/ice_hongsi/", "website": "https://smartstore.naver.com/icehongsiart?fbclid=PAZXh0bgNhZW0CMTEAAaf2WwXaaBZvoHahEACGixkwzuQ8wJJm9PoHoV39Fgn0pz6xDXiJWs5HGCBCtQ_aem_R04XAVM1f-YE5fmxsk9cvQ", "intro": "포근한 귀여움을 그립니다"}, "Q25": {"instagram": "https://www.instagram.com/xas2ko", "website": "https://link.inpock.co.kr/xas2ko", "intro": "귀엽다고 생각하는 걸 그려요ᰔ아닐수도.."}, "F14": {"instagram": "www.instagram.com/acornzzi", "intro": "아콘찌의 포근한 마을"}, "O28": {"instagram": "https://www.instagram.com/ato_and_bandi/", "intro": "큐트하고 키치한 팬시샵 아토앤반디입니다.\n롭이어 토끼 아토와 소녀 반디를 그려요 :)"}, "D09": {"instagram": "https://www.instagram.com/9_o_clock_bonnie/", "website": "https://mkt.shopping.naver.com/link/681aadb146ee00714bd1497f", "intro": "Happy Bedlinton Day!\n베들링턴테리어 바니와 티니\n그리고 상냥한 소녀 클로이의 일상"}, "I02": {"instagram": "https://www.instagram.com/_ahnhyunjung/", "intro": "일상 속 여행을 담아요"}, "G06": {"instagram": "https://www.instagram.com/angora_lora", "website": "https://smartstore.naver.com/angoralora"}, "Q35": {"instagram": "https://www.instagram.com/angkku8_8?igsh=MXdnNmdzaTFxeDE4Ng%3D%3D&utm_source=qr", "website": "https://blog.naver.com/angkku8/223986283490", "intro": "일러스트 모음"}, "F01": {"instagram": "https://www.instagram.com/_aeppol", "intro": "깊은 숲속에서 살아가는 한 소녀의 이야기를 통해,\n자연이 주는 위안과 행복을 그립니다."}, "P10": {"instagram": "instagram.com/afternoonch", "website": "afternoonch.com", "intro": "우리가 눈치챈 장면들"}, "P25": {"instagram": "https://www.instagram.com/aegongsclub/", "intro": "지치고 웃픈 직장인의 마음을 햄스터가 대신 말해드립니다.\n회사에서 쌓인 스트레스, 웃으며 털어내는 인스타툰을 그립니다. 직장인의 현실을 담은 굿즈들과 웃음을 함께 전해드릴게요."}, "G03": {"website": "ya0n.creatorlink.net", "intro": "어떤 세계를 그립니다."}, "G19": {"instagram": "https://www.instagram.com/ds_tape", "intro": "캔버스에 감정의 선과 색을 담아내는 그림작가입니다."}, "D22": {"instagram": "https://www.instagram.com/yangchee_", "intro": "여행지에서 마주한 풍경을 따뜻한 색감과 감성적인 분위기로 그립니다."}, "M17": {"instagram": "https://www.instagram.com/anodear.studio/?__pwa=1", "website": "https://smartstore.naver.com/anodearstudio", "intro": "𝑯𝒆𝒂𝒓𝒕 𝒊𝒔 𝒏𝒐𝒕 𝒂𝒏 𝒂𝒅𝒖𝒍𝒕 𝒚𝒆𝒕.\n귀여운 것들을 통해\n마음속 동심을 지켜주고 또 선물하는 브랜드입니다"}, "C23": {"instagram": "https://www.instagram.com/a_scoop_of_p", "website": "https://smartstore.naver.com/ascoopofp", "intro": "Let's record today with cute things!\n하루를 좀 더 귀엽게 기록할 수 있는 제품을 디자인하고 만듭니다."}, "K43": {"instagram": "instagram.com/inlastnights_dream", "website": "https://www.picturebook-illust.com/author-gallery/room/63037", "intro": "현실에서는 존재할 수 없는 아스라한 꿈의 조각들.\n그림이기에 가능한 세계를 그리는 몽상기록가 전위로(WELOW)가 반짝반짝 빛나는 몽상의 순간들을 기록합니다."}, "M34": {"instagram": "https://www.instagram.com/autumn.fruits", "website": "https://smartstore.naver.com/afoo", "intro": "포근포근 빨간 베레모를 쓴 새침한 고양이, 빤딱빤딱 갈색 구두를 신은 어리바리 고양이. 사람과 닮아 웃기고 귀여운 고양이들의 이야기를 그리고 굿즈로 제작합니다."}, "T21": {"website": "https://www.storexppen.kr/", "intro": "XPPen은 디지털 드로잉 타블렛, 태블릿 등 혁신적인 제품을 연구/생산/판매하는 세계적으로 유명한 디지털 아트 혁신 브랜드입니다."}, "I05": {"website": "https://blog.naver.com/endand_may", "intro": "일상 기억의 순간을 포슬한 색연필 느낌으로 그려냅니다."}, "J49": {"instagram": "https://www.instagram.com/moccc.au/", "website": "https://www.moccc.au/", "intro": "자연과 일상의 감정들은 저의 작업의 출발점 입니다. 수작업의 따뜻함과 디지털 도구의 유연함을 결합한 감각적이고, 정서적으로 공명하며, 공간과 사람을 연결하는 디자인을 선보입니다."}, "L23": {"instagram": "https://www.instagram.com/yeondinn/", "website": "https://picturebook-illust.com/author-gallery/room/71855", "intro": "안녕하세요. 일러스트레이터 연딘입니다 ☺️\n여름을 날 땐 덥고 지치지만 겨울을 맞이하면 여름의 날들이 그리워지는 것처럼,\n지나고 보면 특별하게 느껴지는 일상의 순간들을 그립니다."}, "F21": {"instagram": "instagram.com/0_stel/", "website": "https://smartstore.naver.com/", "intro": "오일파스텔로 고양이들의 포근하고 따사로운 일상을 담아내는 작가 연스텔입니다."}, "N01": {"instagram": "https://www.instagram.com/yeran_illust", "intro": "일상에서 쉽게 지나칠 수 있는 풍경에 다채로운 색과 빛을 더해 여러가지 이야기를 전하는 일러스트레이터 ‘예란’입니다. 누구나 공감할 수 있는 편안한 그림을 지향합니다."}, "H18": {"instagram": "www.instagram.com/yeah_atelier", "intro": "수채화로 떠나는 여행, 예지킴과 함께 해요."}, "I12": {"instagram": "https://www.instagram.com/yeel_e?igsh=NGRwZnJ4bTExbXFj&utm_source=qr", "website": "https://www.threads.com/@yeel_e?igshid=NTc4MTIwNjQ2YQ==", "intro": "일러스트 드로잉 작가입니다."}, "T11": {"instagram": "https://www.instagram.com/dailycutie_shop/", "intro": "매일 새로운 귀여움, 오늘의귀여움!\n오늘의귀여움은 독자적인 캐릭터 IP를 기반으로 캡슐 토이 시리즈와 라이프 스타일 상품을 전개하는 캐릭터 IP 브랜드입니다."}, "M47": {"instagram": "https://www.instagram.com/oddlee/", "intro": "조금은 이상하고 조금은 사랑스러운\n작은 이야기들을 그리고있는 오드리라고 합니다."}, "Q50": {"instagram": "https://www.instagram.com/platypupu_paperart", "intro": "디지털 시대, 멸종된 동물을 종이로 복원하는 페이퍼아티스트이자 생물을 주제로 작업하는 일러스트레이터입니다."}, "P37": {"instagram": "https://www.instagram.com/ori_andyou", "intro": "🎀 동화 같은 우리의 순간 🎀"}, "R14": {"instagram": "https://www.instagram.com/oasi.z_/", "website": "https://www.behance.net/zoewu0806d64a", "intro": "A BRAND THAT SHARES LIFE THROUGH ILLUSTRATIONS\n🌀\n(Based in Taiwan,Taipei)(🇹🇼)"}, "U13": {"website": "https://weo.co.kr/"}, "G10": {"instagram": "https://www.instagram.com/okiki_diary/", "website": "https://www.okikidiary.com", "intro": "오키키는 일상에서 영감을 얻어 그림을 그리고 소통하는 브랜드 입니다.\n작고 귀여운 캐릭터들과 함께 이야기를 만들어 나가고 있습니다."}, "H16": {"instagram": "https://www.instagram.com/oturry_/", "intro": "해달 터리와 함께 음식을 그려요"}, "C32": {"instagram": "https://www.instagram.com/_otto_art/", "website": "https://www.youtube.com/@TTOart"}, "M49": {"instagram": "https://www.instagram.com/on_0o0", "intro": "안녕하세요\n따뜻하고 마법같은 색감의 그림을 그리는 온입니다."}, "L44": {"instagram": "https://www.instagram.com/on.dol_/", "intro": "온기를 담아 작품을 만드는 돌팔이 작가 온돌 입니다 ^~^"}, "H35": {"website": "https://linktr.ee/holafriends", "intro": "안녕하세요. 귀여움의 정상에 올라가고 싶은 올라프렌즈\n입니다! 일러스트를 기반으로 귀엽고 따스한 작품들을\n그리고 만듭니다."}, "N09": {"instagram": "https://www.instagram.com/yomahon/"}, "P27": {"instagram": "https://www.instagram.com/yoa.gif/", "website": "https://x.com/yoagif", "intro": "요괴요괴하고 아스트랄합니다.."}, "C16": {"instagram": "https://www.instagram.com/y_oyori/", "intro": "내 안의 소녀감성을 깨워보자!"}, "Q28": {"instagram": "https://www.instagram.com/younyounsama/profilecard/?igsh=MWNjYmR2OGkydjVqaw==", "website": "https://blog.naver.com/wedding83", "intro": "꽃과소녀 한복그리기를 좋아하는 일러스트레이터 욘욘입니다."}, "R50": {"website": "https://comic.naver.com/bestChallenge/list?titleId=806433", "intro": "귀여운 토끼 필두 와 함께 해요!"}, "M42": {"instagram": "https://www.instagram.com/oneandonehalf.studio/", "intro": "따뜻함으로 당신을 채워주고 싶은\n마음으로 그림을 그려요.\n온전한 당신의 하나에 나의 반을 더해줄게요.\n나의 마음이 당신의 옆에 머물며\n온기가 가득 차 넘칠 수 있길 바라요."}, "J51": {"instagram": "https://www.instagram.com/wol_bok", "intro": "휴식을 모티브로, 콘테와 디지털 작업을 통해 감정의 결을 담은 그림을 그립니다.\n상징적 공간 검은 정원과 그 속의 캐릭터들은 관객에게 위로와 영감을 건네는 작은 피난처가 됩니다"}, "B06": {"instagram": "https://www.instagram.com/winnie_village", "intro": "행복한 일상을 그리는 \n위니빌리지입니다."}, "L31": {"instagram": "https://www.instagram.com/from.yu_d/", "website": "https://www.fromyu-d.com/", "intro": "일상 속 작은 행복과 긍정적인 에너지를 그려냅니다.\nFresh your day!"}, "M25": {"instagram": "https://www.instagram.com/yura_d.illust?igsh=eW9nNnV4azYzdzF3", "intro": "햇살과 초록, 그리고 고양이의 평온한 순간을 그립니다."}, "I53": {"instagram": "https://www.instagram.com/gionharo/", "intro": "웹툰 작가, 데뷔작 (유럽에서 100일)"}, "I27": {"instagram": "https://www.instagram.com/urr.official", "website": "https://www.urrstore.com/", "intro": "귀여움의 시작 !\n\n💗 작고 소소한 행복이 모여\n커다란 행복을 만들어가는 이야기"}, "G38": {"instagram": "https://instagram.com/yoosh.ink/", "intro": "90년대 셀 애니메이션의 향수를 바탕으로, 일상과 판타지, 과거와 현재가 교차하는 아름다운 순간들을 그립니다.\n\n대표 오리지널 프로젝트 : 크리스탈 가디언즈"}, "H38": {"instagram": "https://www.instagram.com/bluegirl128", "intro": "수채풍의 동화 일러스트를 지향해요.\n\n파인아트, 디지털 아트를 오고가며\n수채화만의 청량하면서 은은한 아름다움을\n전달하고 싶어요."}, "V27": {"instagram": "https://www.instagram.com/hookka.hookka.studio/", "website": "https://uoco.kr/", "intro": "유오코와 후후스는 일상에 둥글고 다정한 한켠을 지어 나가며, 말랑한 감성과 오리지널 IP를 바탕으로 오래도록 사랑받고 아껴질 물건과 이야기를 만들어가는 라이프스타일 브랜드입니다."}, "O29": {"instagram": "https://www.instagram.com/uhamira_/", "website": "https://x.com/uhamira_", "intro": "동양의 정서를 섬세하게 담아 \n현실 속 작은 판타지를 만듭니다"}, "M18": {"instagram": "https://www.instagram.com/yoohee_322", "website": "https://twitter.com/yoohee_322", "intro": "다정이 흐르는 세계를 그리는 유히입니다. 색연필, 수채화를 기반으로 한 수작업과 따스한 느낌의 디지털 작업으로 그림책, 동화 삽화나 패키지, 굿즈 등 다양한 작업을 하고 있습니다."}, "D16": {"instagram": "https://www.instagram.com/yyoondong?igsh=Z3VkM3N5MDNld3F2&utm_source=qr"}, "Q30": {"instagram": "https://www.instagram.com/yoonsum.illust/", "website": "https://yoonsum.myportfolio.com/2023", "intro": "하루의 작은 순간들 속에 스며든, 나를 아끼고 돌보는 마음을 기록합니다."}, "Q45": {"instagram": "https://www.instagram.com/yoonjii7/", "website": "https://yoonjii7.com/", "intro": "안녕하세요. 일러스트레이터 yoonjii7(윤진)입니다.\n자연과 일상의 사랑스러운 것들을 모아 작은 세상으로 표현합니다. 소소한 이야기를 담은 봄바람같이 따뜻한 그림을 그려요."}, "J53": {"instagram": "https://www.instagram.com/22yyung", "intro": "piece of peace 🏝️"}, "M31": {"instagram": "https://instagram.com/__eunhwan", "website": "https://www.youtube.com/@__eunhwan", "intro": "노스탤지어를 바탕으로 소녀와 \n동화적 이미지를 \n중심으로 작업하며, \n스쳐 지나간 감정과 기억을 \n몽환적이고 섬세한 감성으로 표현합니다."}, "O25": {"instagram": "https://www.instagram.com/ennggu/", "intro": "작지만 귀여운 친구들, 큐티즈 !"}, "Q11": {"instagram": "www.instagram.com/e.in_art", "intro": "당신은 너무 사랑스러워요.\n아주 소중하지요.\n충분히 잘 하고 있어요. \n\n-사랑을 담아, 이나트  :-)"}, "Q47": {"instagram": "https://www.instagram.com/yi.leut/", "website": "https://yileut.com/", "intro": "당신에게 귀여움이 필요할 때✨"}, "P38": {"instagram": "https://www.instagram.com/_2soh/"}, "H15": {"instagram": "https://www.instagram.com/pencilmood_?igsh=NXVxNnQ4bmplenNu&utm_source=qr", "intro": "스쳐가는 일상의 빛나는 순간들을 그립니다."}, "R23": {"instagram": "https://www.instagram.com/ie_sso/", "intro": "네잎클로버보다 세잎클로버가 더 좋은 작가의 행복해지는 이야기 ☘️💭"}, "Q12": {"instagram": "https://www.instagram.com/e.u.ningning/", "intro": "안녕하세요, 평온한 일상을 꿈꾸는 디자이너 /일러스트레이터 이유닝닝입니다.\n모든 작업은 인스타그램에서 보실 수 있습니다."}, "G35": {"instagram": "https://www.instagram.com/jaesdrawing", "intro": "순간의 감정을 기록합니다."}, "M54": {"instagram": "https://www.instagram.com/iz.olz/", "intro": "찰나의 반짝임을 그림으로 담습니다"}, "G37": {"instagram": "https://www.instagram.com/with_2ho/", "website": "https://crepe.cm/ko/@with_2ho", "intro": "반복되는 일상 속 잠시 떠난 여행처럼, 빛과 계절이 담긴 풍경을 그립니다. 오래 기억에 남는 쉼을 전하고 싶습니다."}, "R43": {"instagram": "https://www.instagram.com/intadayo", "intro": "안녕하세요. 서브컬쳐 기반의 캐주얼 일러스트를 그리고 있습니다."}, "B29": {"instagram": "https://www.instagram.com/intern.dugi", "intro": "아씨를 모시는 인턴집사 박두기입니다"}, "Q10": {"instagram": "www.instagram.com/arang_illust", "intro": "수채화로 전하는 평화로운 위안"}, "Q43": {"instagram": "https://www.instagram.com/imperfectchiiild_?igsh=ODgxNGNiMWEzaTZt&utm_source=qr", "intro": "⭐️🩹"}, "G01": {"instagram": "https://www.instagram.com/zkzk_studio/", "intro": "귀여운게 좋아서 자꾸자꾸!"}, "I11": {"instagram": "https://www.instagram.com/jeonyr22", "intro": "페이퍼 콜라주로 만든 사랑스러운 나의 반려 식물들"}, "H46": {"instagram": "https://www.instagram.com/ninano_boram/", "intro": "🧛🏻‍♀️ 사람을 그리는 사람 (부스: D25)"}, "O38": {"instagram": "https://www.instagram.com/jal___sara/", "intro": "안녕하세요 엉뚱하고 귀여운 소녀들을 그리는 잘사라입니다."}, "K03": {"instagram": "https://www.instagram.com/jang_dding", "intro": "장띵은 캐릭터와 만화적 표현을 중심으로 예술과 상업의 경계를 넘나드는 비주얼 아티스트이다. 독창적인 그림체와 유쾌한 상상력을 바탕으로, 즐거움이 담긴 자신만의 세계를 펼쳐나간다."}, "P01": {"instagram": "https://www.instagram.com/janghyesooooo", "website": "https://janghyesooooo.creatorlink.net/", "intro": "일상 속 빛과 그림자를 담은 풍경을 그립니다."}, "M39": {"instagram": "https://www.instagram.com/jaguartree.studio/", "website": "https://www.behance.net/jaguartree", "intro": "따뜻한 시선으로 그리는 재거트리의 세계"}, "Q36": {"instagram": "www.instagram.com/jaei_house", "intro": "인물 주력 씰스티커, 문구, 굿즈를 제작하는 재이하우스 입니다."}, "G08": {"instagram": "https://www.instagram.com/woo_m.ool/", "intro": "애틋함 감정을 그립니다."}, "Q44": {"instagram": "https://www.instagram.com/jung_oneeee?igsh=MWYzdmhsY3N2czM3aA%3D%3D&utm_source=qr", "intro": "테이블 위의 꽃, 햇빛 드는 부엌, 한낮의 공원처럼 평범하지만 기억에 남는 순간을 그립니다. Jung one이 수집한 장면들이 당신의 일상 속에서도  따뜻한 정원이 되길 바랍니다."}, "K24": {"instagram": "https://www.instagram.com/jung_in01/", "website": "https://x.com/jung_in01"}, "H01": {"instagram": "https://www.instagram.com/jennyvillage/", "intro": "일상의 작은 행복, 제니빌리지"}, "I50": {"instagram": "instagram.com/jenniferdbkim", "website": "are.na/jennifer-kim-byybb9-osk/channels", "intro": "잊혀진 시간을 찾아서..."}, "P06": {"instagram": "https://www.instagram.com/jerry.bbang/", "intro": "말랑한 귀여움을 만들고 따뜻하게 구워요"}, "Q01": {"instagram": "https://www.instagram.com/hej_jeje/", "intro": "짧은 머리 소녀 율무와 하얀 호랑이 어흥이를 그려요.\n당신의 일상 속 다정한 위로가 되길..."}, "O30": {"instagram": "https://www.instagram.com/zekibear?igsh=MWxpNms2OHVjNjJmMg%3D%3D&utm_source=qr", "intro": "안녕하세요 제키베어의 제키입니다。( ˘͈ ᵕ ˘͈ )ꕤ.˖。♡"}, "Q26": {"instagram": "https://www.instagram.com/zefio_illustrator/", "intro": "안녕하세요. 제피오 입니다. ^^\n\n저는 동물과 클래식카를 컨셉으로 일러스트 작품활동을 하고 있습니다."}, "H06": {"instagram": "https://www.instagram.com/jyening_/", "website": "https://www.picturebook-illust.com/author-gallery/room/73157", "intro": "따뜻함을 전하는 졔닝입니다"}, "H09": {"instagram": "https://www.instagram.com/jyejye_art/", "website": "https://jyejye.kr/", "intro": "밤밤이와 친구들의 따뜻한 일상을 그립니다."}, "I30": {"instagram": "https://www.instagram.com/hiojjo", "intro": "조금씩 그림그리는 조랑스튜입니다\n만나서 반갑습니다"}, "J15": {"instagram": "https://www.instagram.com/joyandle", "intro": "계절 속 숨겨진 이야기를 그립니다.\n그 안에는 우리가 살아가는 데 필요한 작은 힌트와 \n마음을 풀어주는 다정한 위트가 숨어 있다고 믿습니다."}, "H43": {"instagram": "www.instagram.com/zoizom", "intro": "한 선으로 일상과 마음을 그리는 조이좀입니다."}, "B40": {"instagram": "https://www.instagram.com/jollygeestudio/?hl=ko", "intro": "✨Jollygee for Every Moment, JOLLYGEE STUDIO✨\n\n키치함과 즐거움 가득한 '졸리지 스튜디오' 입니다!"}, "N51": {"instagram": "www.instagram.com/kiskeco/", "website": "blog.naver.com/kiskeco", "intro": "작가의 일상과 추억을 기념하는 그림, 상상속에서 일어나는 일들을 그림으로 그리고 있습니다.\n\n그리고 연재했던 웹툰과 관련된 그림을 그립니다."}, "L39": {"instagram": "https://www.instagram.com/jour_di/", "intro": "+ 모든 것 위에 사랑을 더하기 +\n작은 오리 디어와 하루 속 사랑스러운 순간을 찾아 전해요!"}, "O36": {"instagram": "http://instagram.com/icecream_juba", "intro": "일러스트레이터 주바입니다."}, "H30": {"instagram": "https://www.instagram.com/juaooju/#", "website": "https://brunch.co.kr/@juaooju", "intro": "주아우주는 동물과 사람이 함께 머무는 감정을 글과 그림으로 기록합니다."}, "B37": {"instagram": "https://www.instagram.com/juimjuim_official/", "website": "https://x.com/JUIM_official", "intro": "병아리만두 삠과 귀여운 동화 속 세상을 만들어요💛"}, "I14": {"instagram": "https://www.instagram.com/joopression"}, "P13": {"instagram": "https://www.instagram.com/jigueki"}, "O01": {"instagram": "https://www.instagram.com/jibleart", "intro": "우리나라의 겨울 철새이자 세상에서 가장 귀여운 새. 오목눈이 캐릭터를 그려요."}, "B14": {"instagram": "https://www.instagram.com/jee_yoom/", "intro": "작은이야기들을 그려나가는 지윰입니다 :)"}, "B03": {"instagram": "https://www.instagram.com/jjokkomicat/", "website": "https://smartstore.naver.com/jjokkomicat", "intro": "어서오세요! 고양이공방 \n쪼꼬미캣 입니다 :3\n\n그림그리는 쪼와 바느질하는 꼬미가\n만드는 귀여운 일상을 함께해요!"}, "B16": {"instagram": "https://www.instagram.com/chocozy_family/", "website": "https://link.inpock.co.kr/chocozy_family", "intro": "쪼그만 꼬마 지구탐사대의 일상을 그립니다."}, "C01": {"instagram": "https://www.instagram.com/jjo_ramzi/", "website": "https://www.jjoramzi.com", "intro": "일상의 기록에 작은 웃음 드리는\n귀여운 이야기를 그립니다"}, "Q20": {"instagram": "https://www.instagram.com/zzoya", "intro": "몽글몽글 따뜻한 그림을 그리는 작가 쪼야입니다"}, "H28": {"instagram": "https://www.instagram.com/jjonglove01", "intro": "안녕하세요! 쫑스튜디오입니다."}, "K52": {"instagram": "https://www.instagram.com/jjugguli/?hl=ko", "intro": "쭈꿀해도 행복해"}, "K06": {"instagram": "https://www.instagram.com/childhood_100", "intro": "어린 시절의 꿈을 그립니다."}, "J08": {"website": "chabstar.com", "intro": "고양이 뿐만 아니라 지구상의 모든 동물들과 자연을 모티브 삼아 공간에 어울릴 수 있는 감성적인 일러스트로 그려내고 있습니다."}, "V50": {"instagram": "https://www.instagram.com/chachaqwertyui/", "intro": "소녀와 도시를 그리는 채널오입니다."}, "M02": {"instagram": "https://www.instagram.com/chae_min_g/", "website": "https://chaeming.myportfolio.com/work", "intro": "꽃말과 한국 전통미술의 상징을 통해 개인의 서사를 암호화된 그림으로 기록합니다."}, "R02": {"intro": "안녕하세요! 귀여운 그림으로 일상을 나누고 있는 챈입니다 💙 인스타그램과 네이버베도에 <오늘의 후기>라는 만화를 그리고 있어요!"}, "G18": {"instagram": "https://www.instagram.com/chapchabiiiii321/", "website": "https://chapchabii.com", "intro": "✦ 디지털드로잉에 손그림 감성 한 스푼\n✦ 아이패드 수채화&색연필 일러스트\n💌 브랜드 협업 & 작업 문의 : chapchabii@naver.com"}, "V36": {"instagram": "https://instagram.com/choryeong_official", "website": "https://smartstore.naver.com/choryeong", "intro": "책장 속에 피어난 작은 숲, 꽃과 자연의 조화를 끈과 비즈로 엮어낸 핸드메이드 책갈피"}, "G25": {"instagram": "https://www.instagram.com/greenut90/", "website": "https://www.youtube.com/greenut", "intro": "greenut + peanut = greenut, 초록땅콩.\n흘러가는 시간 속 시선이 잠시 머무는 순간을 담고자 하는 일러스트레이터 greenut, 초록땅콩입니다."}, "M21": {"instagram": "https://www.instagram.com/choi__._.__/", "intro": "최쩜쩜이에요"}, "E30": {"website": "chuchou.co.kr", "intro": "환상적이고 어딘가 기묘한 이야기를 담은 그림을 그립니다"}, "D34": {"instagram": "https://www.instagram.com/choosyabout_official/", "website": "https://smartstore.naver.com/choosyabout", "intro": "취향을 찾고 취향을 만듭니다."}, "B36": {"instagram": "https://www.instagram.com/cheeryiclub/", "website": "https://x.com/CheeryiClub", "intro": "Cheerful한 에너지를 주는 치리클럽(Cheeryiclub) 🍒!"}, "P29": {"instagram": "instagram.com/chimoart_", "intro": "안녕하세요 치모입니다!💗 방문해주셔서 감사합니다!\n서일페 v.21에서 뵙겠습니다🙇‍♀️"}, "I31": {"instagram": "https://www.instagram.com/", "website": "https://x.com/PipiChacha2", "intro": "커피새 피피&홍차냥 차차의 랜선카페... 였지만, 이제는 슬슬 현실로 나올 때가 된 거 같다구요!"}, "J33": {"instagram": "https://www.instagram.com/kath_illust/", "website": "https://kathillust.com/", "intro": "색연필로 음악을 그립니다."}, "H17": {"instagram": "https://www.instagram.com/comflex_9b/", "intro": "컴플렉스(COMFLEX)는 가상의 캐릭터들이 모인 예술 크루입니다. 각 캐릭터는 불안, 외로움, 허무함, 열등감 같은 창작자의 내면을 반영한 존재이며 작업의 주체입니다."}, "E08": {"instagram": "https://www.instagram.com/it_kki/", "website": "https://cakeehouse.com", "intro": "cakee"}, "U12": {"instagram": "https://www.instagram.com/kodo.and.lolly/", "website": "https://bluebirdc.co.kr/", "intro": "코도와 롤리의 고독상점 (Lonely Market) 에 놀러오세요!\n\n청년 외로움 문제를 문화예술로 해결하는 소셜벤처 (주)블루버드씨가 함께합니다."}, "P26": {"instagram": "https://www.instagram.com/coraltree_jj"}, "K19": {"instagram": "https://www.instagram.com/cosmo_exp", "website": "https://x.com/Cosmo_Exp"}, "P22": {"instagram": "www.instagram.com/kossaricoo", "website": "https://m.smartstore.naver.com/kossaricoo", "intro": "마음의 안식처가 될 수 있는 포근한 동화를 그리고 있는 코싸리쿠입니다 :)\n어서 오세요, 고양이들이 전하는 따스한 이야기가 기다리고 있답니다."}, "A21": {"instagram": "https://www.instagram.com/koconenne/", "intro": "꿈처럼 포근함을 그리는 코코넨네입니다 zZz .."}, "V16": {"instagram": "instagram.com/cohlabi", "website": "cohlabi.com", "intro": "콜라비는 아트, 캐릭터, 콘텐츠 등 다양한 IP를 기반으로 브랜드와 창작자의 콜라보레이션을 매칭, 기획, 실행하는 에이전시입니다."}, "M28": {"instagram": "http://www.instagram.com/kongdung_house", "intro": "다섯명의 소녀들과 작은 동물을의 이야기를 그리고 있는 \"콩둥이네\" 입니다."}, "P45": {"instagram": "https://www.instagram.com/cureyom/", "intro": "누구든 머물 수 있는 세상을 담는 작가 쿠레욤입니다."}, "B23": {"instagram": "https://www.instagram.com/cooking._.cookie", "intro": "호랑이 쿠랑이와 사자 쿠왕이, 토끼 쿠끼의 귀여운 일상을 그려냅니다"}, "F29": {"instagram": "https://www.instagram.com/crabbito.artstudio/", "intro": "달의 선장 세계를 중심으로 빛과 어둠, 그리고 내면의 변화를 탐구하며. 섬세한 선과 겹겹의 이미지로 자신만의 빛을 찾아가는 여정을 그립니다.\n@crabbito.artstudio"}, "F04": {"instagram": "www.instagram.com/crayon.rabbit", "intro": "알록달록 빛나는 색감으로 그림 그려요\n(오일파스텔, 색연필, 마카)"}, "P04": {"instagram": "instagram.com/creamy.crumbz", "intro": "stick a creamy crumbz!"}, "H08": {"instagram": "https://instagram.com/crazy_yaa_", "intro": "곁눈질하는 소녀, 크야"}, "I21": {"instagram": "https://www.instagram.com/clevertory_lab/", "intro": "📚하루의 감성과 작은 이야기✨\n\n오늘은 어떤 📖페이지를 넘겨 볼까요?"}, "Q18": {"instagram": "https://www.instagram.com/chloe_artgarden", "intro": "일러스트레이터"}, "K50": {"instagram": "https://www.instagram.com/lab_clone/", "intro": "우주를 여행하는 친구들의 이야기를 그립니다."}, "P40": {"instagram": "https://www.instagram.com/kky_ron/", "intro": "키론은 대담하고 화려한 색채를 통해 강렬한 시각적 인상을 만들어내는 아티스트다. 다양한 색상을 조화롭게 활용하여 작품마다 자신만의 색채 언어를 힙하게 구축해 나가고 있다."}, "R21": {"instagram": "https://www.instagram.com/kingeyestory?igsh=MThmNDBsMXd6MndrcA%3D%3D&utm_source=qr"}, "K51": {"instagram": "www.instagram.com/tinypetvoyage", "intro": "콧수염 달린 강아지, 강저씨와 친구들!"}, "L46": {"instagram": "https://www.instagram.com/potato0_t/", "intro": "집 어딘가에서, 탁자 밑에서 사람들 몰래 음식을 가져가는 요정들의 이야기를 그립니다"}, "R18": {"instagram": "instagram.com/taerimart", "website": "X.com/taerimart", "intro": "아날로그 방식의 수작업을 합니다."}, "G53": {"instagram": "https://www.instagram.com/taptaptoptop/", "website": "https://smartstore.naver.com/taptaptoptop", "intro": "탭 탭 탑 탑\n지나가는 소리\n귀 기울이기"}, "H27": {"instagram": "https://www.instagram.com/nonbiri_enikki/", "intro": "익숙하지만 새로운, 소중한 발견!"}, "F27": {"instagram": "https://www.instagram.com/terrybox_/"}, "A14": {"instagram": "https://www.instagram.com/tetrapod.melontea/", "website": "https://x.com/tetrapod_melont"}, "Q37": {"instagram": "https://instagram.com/ltehi", "website": "https://notefolio.net/ltehi", "intro": "마카 일러스트레이터 테히입니다. 오랫동안 그려온 매일을 그립니다."}, "Q53": {"instagram": "https://www.instagram.com/take_2t_2asy?igsh=cnFtNmt1bDNucjRv&utm_source=qr", "intro": "후니와 강아지 쏭의 이야기를 그리고 있습니다~"}, "N18": {"instagram": "https://www.instagram.com/tokkiya_diary/", "intro": "토끼야일기입니다!"}, "R42": {"instagram": "https://www.instagram.com/espiga_i", "intro": "물방울에서 피어난 식물을\n \n가볍고 유쾌한 시선으로 그리고, \n흙으로 한방울, 한방울 빚어서 담아냅니다.\n\nCeramics and illustrations"}, "N35": {"instagram": "www.instagram.com/tomaytravel", "intro": "오늘 날의 보살은 어떤 모습일까"}, "C24": {"instagram": "https://instagram.com/topping_goods", "website": "https://smartstore.naver.com/topping_goods", "intro": "오늘도 행운 토핑중! 🍀"}, "D37": {"instagram": "https://www.instagram.com/earlysummer_studio", "website": "https://m.blog.naver.com/love_pagwa", "intro": "🎨 따뜻함과 연약함 속에서 수집한 희망의 조각들"}, "M15": {"instagram": "https://www.instagram.com/padohae_studio/"}, "K14": {"website": "https://www.behance.net/seheechae", "intro": "(2015~)\n일러스트레이터 파이입니다.\n소녀와 자연에 대해서 그리며 수많은 책과 광고에 그림을 실었습니다."}, "Q14": {"instagram": "https://www.instagram.com/fire_brush_/?hl=ko", "website": "https://x.com/rlawodn40", "intro": "Sci-fi 장르의 기계와 캐릭터 일러스트를 그립니다"}, "H04": {"instagram": "https://www.instagram.com/ivory_ppappu", "website": "https://smartstore.naver.com/ppappu", "intro": "파랗고 푸르른 풍경을 그립니다.\n세상과 맞닿아 있으면서도 다정히 보호받는 공간인 온실에서 위안과 평안을 느낍니다.\n분주한 일상 속 잠시 머물러 숨을 고르는 작은 쉼이 되기를 바래요"}, "C09": {"instagram": "https://www.instagram.com/palbegae", "intro": "일상에 스며드는 포근한 일러스트를 그립니다."}, "D19": {"instagram": "https://www.instagram.com/xx8_mon/", "intro": "일러스트레이터, 타투이스트"}, "D21": {"instagram": "https://www.instagram.com/perms__/", "intro": "다 뽀까버릴거야"}, "M36": {"instagram": "https://www.instagram.com/pumpum_rum_/", "website": "https://x.com/pumpum_rum_", "intro": "로망의 소녀들을 그리는 펌펌입니다..♡"}, "V39": {"instagram": "https://www.instagram.com/dearpost_", "website": "https://www.dearpost.kr/", "intro": "흐린 날을 담는 편지 가게"}, "M11": {"instagram": "https://www.instagram.com/pyunghwa_jogak?igsh=cjRiaWtlengwaHdv&utm_source=qr"}, "D31": {"instagram": "https://www.instagram.com/for_normal/", "intro": "생각을 그리는 일러스트레이터 포노멀입니다. 평범하지만 특별한 순간을 그리고 있습니다."}, "Q42": {"instagram": "https://www.instagram.com/forestree_m.y?igsh=YnFiN2g4OTl2ZmV2&utm_source=qr", "website": "https://youtube.com/watch?v=n47xbgAF3rc&si=h1eTDdnWMVDlBUIZ", "intro": "사랑하는 것들을 하나씩 담아낸 기록들이 모여 작은 나무가 되고, 숲이 되듯,\n 언젠가 이곳이 많은 이들이 편안히 머물다 갈 수 있는 따뜻한 쉼의 공간이 되기를 바랍니다."}, "C15": {"instagram": "https://www.instagram.com/p.o.s.o.m/", "website": "https://twenty.style/profile/posom", "intro": "작고 소중한 털뿜뿜 친구들!\n아기 고양이 먕먕이의 말랑한 일상을 그려요"}, "L29": {"instagram": "https://www.instagram.com/poetico.kr/", "website": "https://www.sixshop.com/poetico/portfolio", "intro": "귀여움 수집가 포에티코 입니다.\n일러스트를 그리고 제품을 만듭니다.\nPOETIC COLLECTION, POETICO"}, "Q02": {"instagram": "www.instagram.com/iampozi/", "website": "https://www.wadiz.kr/web/campaign/detail/280939?srsltid=AfmBOoprWNiJnjkAuCQPcQ_5eBIX6sF3uB2CdLuFur4EhjxbAj9OVLQi", "intro": "이름으로 하나뿐인 작품을 그리는 \n이름캐리커처작가 포지입니다 :)"}, "E31": {"instagram": "https://www.instagram.com/pakazoko", "website": "https://www.poralee.com", "intro": "교차되는 삶 속의 사랑과 존재를 그립니다. \n글과 회화를 기반으로 출판 작업, 개인책 작업, 전시 활동을 합니다.\n가족과 함께 책 읽고 수영하고 뜨개하는 매일을 보냅니다."}, "R37": {"instagram": "https://www.instagram.com/polticker/", "website": "https://smartstore.naver.com/polticker"}, "K16": {"instagram": "instagram.com/polepipe", "intro": "폴파이프입니다\n일러스트와 디자인 timids를 그립니다"}, "N28": {"instagram": "https://www.instagram.com/pompomroom/", "intro": "Everything fluffy💭\n보송보송 말랑쫀득한 친구들이 사는 여기는 폼폼룸"}, "M22": {"instagram": "https://www.instagram.com/pyo.obj/", "intro": "인간과 자연의 경계를 지운 존재들을 키워내는 일러스트레이터 박준표입니다."}, "P08": {"instagram": "https://www.instagram.com/yeonmyo_", "website": "https://grafolio.ogq.me/profile/연묘/profile", "intro": "귀여운 것을 보거나 먹는 것에서 오는 \n소소한 즐거움 들을 담아\n포근하고 귀여운 작업들을 하고 있습니다."}, "V51": {"instagram": "https://www.instagram.com/cupid_gom/"}, "J03": {"instagram": "https://www.instagram.com/kimjihye_art", "website": "https://nplanet.io/creator/157/", "intro": "푸른림\n희미해진 기억 속 풍경들의 푸르름을 그립니다."}, "I24": {"instagram": "https://www.instagram.com/ppuccii_land/", "intro": "'내가 행복하면 그만이지!!' 마인드를 가진 푸치의 무해한 일상  /  I24로 놀러오세요 ♥"}, "A10": {"instagram": "https://www.instagram.com/pooky.cuti3/", "intro": "푸키큐티는 다꾸와 패션을 넘나드는 귀여운 상상력을 담아 일상 속 귀여운 룩들을 표현하는 브랜드입니다. 다양한 스타일의 ‘귀여움’을 일상에 꾹꾹 눌러 담는, 팬시걸을 위한 브랜드 푸"}, "A04": {"instagram": "https://www.instagram.com/project_chill_7/", "website": "https://smartstore.naver.com/project7", "intro": "당신의 일상을 풍부한 색으로 채워주기 위한 디자인 스튜디오, 프로젝트 칠입니다."}, "L40": {"instagram": "https://www.instagram.com/from.__dream?igsh=MXZrZGkyYndjZnpq", "intro": "몽글몽글 애정하는 것들을 그립니다"}, "O03": {"instagram": "https://www.instagram.com/fromtostudio/", "website": "https://swlee.myportfolio.com/", "intro": "일상과 꿈의 작은 순간들을 그리고 있습니다.\n주로 수작업으로 포근하고 편안한 느낌의 그림을 그립니다."}, "N54": {"instagram": "https://www.instagram.com/f.ring_zzi", "website": "https://smartstore.naver.com/ddochifriends", "intro": "유별나게 귀여운 친구들과 함께 깜찍한 공감을! 큐티 힐링 브랜드 💖프링찌💖"}, "F23": {"instagram": "https://www.instagram.com/pmont_post.mont/", "website": "https://pmont.imweb.me/home", "intro": "💌 rwdlln07@naver.com  |  Pmont은 Post(우편물)과 Mont(산)의 결합어로 '멀리 전달되는 우편물'이라는 의미를 담고 있습니다."}, "G45": {"instagram": "https://www.instagram.com/flu._.peach/", "intro": "복슬복슬한 그림을 그려요"}, "D18": {"instagram": "https://www.instagram.com/theploppyz/", "website": "https://ploppyz.com/", "intro": "당신의 친구 루크"}, "B39": {"instagram": "https://www.instagram.com/peachhfriends", "intro": "🎀LOVE, SPREAD YOUR LOVE.🎀\n피치에이치프렌즈는 ‘가장 아름다운 것, 가장 진짜인 나의 모습’을 찾는 다섯 친구들의 모험기를 담은 브랜드 입니다."}, "J21": {"instagram": "https://www.instagram.com/pixel_wizville", "website": "https://www.pixelwizville.com", "intro": "\"Quiet magic hidden in emotions.\""}, "L21": {"instagram": "https://www.instagram.com/pimtia_aa", "intro": "안녕하세요 핌티아입니다 빈티지하고 아기자기한 감성의 이야기를 그립니다"}, "U11": {"instagram": "https://www.instagram.com/fitting_rm/", "website": "https://www.fit-pl.com/", "intro": "\"우리, 만들고 싶은거 잔뜩 만들어보자!\"\nFIT 출신 크루들의 B-SIDE PROJECT 공작소"}, "B01": {"instagram": "https://www.instagram.com/pink._.rue/", "intro": "핑루만의 감성이 담긴 다양한 일러스트와 포근한 행복을 주는 귀여운 캐릭터들을 만나보세요"}, "N24": {"instagram": "https://www.instagram.com/ping.ping.diary?igsh=YzBxMzRlbXlva3ho&utm_source=qr", "intro": "Hi, I'm Enzi, an illustrator.\nHappy to introduce my work on OCREA."}, "K38": {"instagram": "https://www.instagram.com/hakkobang", "intro": "일러스트레이터 하꼬방입니다 :)\n\n일상 속 작고 소박하지만\n누군가에게는 소중한 이야기들을 그립니다.\n\nE.mail : hakkobang.ingyo@gmail.com"}, "N29": {"instagram": "www.instagram.com/hanagraph_", "intro": "일상의 작은 순간들을 그림으로 이어갑니다."}, "O17": {"instagram": "http://www.instagram.com/hanabi_crayon", "intro": "가장 따뜻한 파란색 풍경. 그 속 희망의 고래"}, "D13": {"instagram": "https://www.instagram.com/dus0192/", "intro": "소중히 머무는 마음을 담아갑니다."}, "H10": {"instagram": "https://www.instagram.com/house__bear/", "intro": "[Illust / Animation / Video Editor]\n푸른 밤의 여정을 그립니다."}, "G39": {"instagram": "https://www.instagram.com/heim._.mm?utm_source=ig_web_button_share_sheet&igsh=ZDNlZDc0MzIxNw==", "intro": "수작업으로 이상향을 그리는 하임입니다:)"}, "Q08": {"instagram": "https://www.instagram.com/halyangaqui/", "website": "https://grafolio.ogq.me/profile/한량아끼/project", "intro": "📧 Email : halyang_aqui@naver.com"}, "P47": {"instagram": "instagram.com/daengurr", "intro": "견습 순찰대 용맹함 수련 중 . . . 🐕"}, "I23": {"instagram": "https://www.instagram.com/___hae.bom", "intro": "\"세상은 아름다워\" 봄 같은 성격을 가진 해달, 해봄이는 육지의 디저트에 빠져 독립해 나와 맛있는 디저트를 찾으러 다니며 친구를 사귀는 이야기랍니다.🦦🍰"}, "O14": {"instagram": "https://www.instagram.com/ahntail6266/", "intro": "낮에는 밖에서 식물과 즐겁게 놀고\n밤에는 토분에서 잠을 자는 고사리 '해들해즈'를 그리는 작가 안테일입니다."}, "J52": {"instagram": "instagram.com/hae_moi.tt", "intro": "타투를 하며 동시에 아름답고 슬프고 귀엽고 재미난 상상을 그리는 해모입니다! CG와 아날로그 작업을 병행하며 최근에는 수채화 작업에 빠져있습니다."}, "G36": {"instagram": "https://www.instagram.com/happy.orange.world/", "intro": "⊹₊˚ 당신의 일상을 채우는 작은 친구, 𝘁𝗶𝗻𝘆𝗺𝗮𝘁𝗲 ˚₊⊹"}, "R27": {"instagram": "https://www.instagram.com/mousyyyy_/", "website": "https://marpple.shop/kr/hamduri", "intro": "햄스터 햄두리와 친구들이 만들어가는 따뜻한 소동물 이야기를 그리고 있습니다."}, "C17": {"instagram": "https://www.instagram.com/haemaroo_toonn", "intro": "인스타툰  <허당 하마 하뽀링> 및 일러스트 & 캐릭터 굿즈 디자인 및 판매, 이모티콘 작업을 하고 있습니다."}, "D36": {"instagram": "https://www.instagram.com/kgproject2/", "website": "https://x.com/kgproject2", "intro": "Heaven Shall Burn... When We Are Gathered"}, "D39": {"instagram": "https://www.instagram.com/hay.oo.studio/", "intro": "헤이 오오 스튜디오는 몽글몽글한 그림체로 다양한 이야기를 만들어 가고 있어요."}, "J14": {"website": "Instagram.com/hellooooog", "intro": "강아지가 너무 좋아요🐕💕\n인스타툰 <봄동툰>\n강아지와 함께 하는 순간 <Tale for tail>"}, "S32": {"instagram": "https://www.instagram.com/bubby.chat", "intro": "Better Together!\nBUBBY & CHAT"}, "J32": {"instagram": "https://www.instagram.com/floating_hwa/", "website": "https://hoyarn.myportfolio.com/", "intro": "달달하고 맛있는 걸 그려요\n\nArtist, Illustrator, YouTuber\n/ Drawing food Lover and\nStationery holic"}, "G07": {"instagram": "https://www.instagram.com/hojak_jill/", "website": "www.from-hojak.com", "intro": "한국의 문화와 정서를 따듯하고 동그란 그림으로 전해요."}, "E29": {"instagram": "https://www.instagram.com/ho_zi_/", "website": "https://litt.ly/ho_zi_", "intro": "penbyhozi@gmail.com"}, "T01": {"website": "https://www.holbein.kr/index.html", "intro": "고품질의 물감, 재료를 제공하여 사람들의 미(美)적 생활을 풍요롭게 하며, 사회에 도움이 되는 기업으로서 일과 경영에 끊임없이 개선을 거듭합니다."}, "N08": {"instagram": "http://instagram.com/hongmua_art", "website": "http://hongmua.com", "intro": "안녕하세요.\n무아를 그리는 작가, 홍무아 입니다."}, "J02": {"instagram": "https://www.instagram.com/hongji_illust/", "intro": "안녕하세요 일러스트레이터 홍지입니다"}, "J22": {"instagram": "https://www.instagram.com/hwartist_achive/", "website": "https://www.behance.net/hwartist/projects", "intro": "저의 작품 세계관은 저의 캐릭터인 화티스트를 주로 영감받은 컨셉에 맞게 \n저의 작품에 그립니다.\n그의 친구들인 콜리킴, 제니퍼, 릴리 등 여러 캐릭들과 함께 작품에 등장합니다."}, "B15": {"instagram": "www.instagram.com/hwang_daram", "website": "www.hwang_daram.com", "intro": "안녕하세요 황다람입니다\n\n토끼귀 햄스터 '쮸' 와 부끄럼이 많은 원숭이 '몽이'의 이야기를 그려갑니다. 남들과 조금은 다르지만 일상 속에서 자신만의 행복을 찾아가는 이야기를 그려요"}, "J25": {"instagram": "https://www.instagram.com/dan_hwang/", "website": "hwangdan.com"}, "C29": {"instagram": "https://www.instagram.com/huhu_e_e", "website": "https://x.com/huhu_ee"}, "L33": {"instagram": "www.instagram.com/heedagarden", "website": "www.heedagarden.com", "intro": "삶은 나만의 정원을 가꾸는 것. 여행,일상 등에서 마주친 것들을 러프하고 자연스럽게 담아내고 있습니다. \n서일페#21 *부스번호 L33*"}, "Q29": {"instagram": "https://www.instagram.com/silk_n_grace/", "website": "https://huire.creatorlink.net/", "intro": "안녕하세요, 찰나와 찬란, 그 어딘가의 감정 속 잔상을 그려내는 일러스트레이터 희레입니다."}, "D04": {"instagram": "https://www.instagram.com/fullmoon_9515", "website": "https://www.withgoods.net/creator-shop/d33pinthesea", "intro": "푸른 빛 몽환을 그리는 흰 달"}, "P15": {"instagram": "https://www.instagram.com/heemingraphics/", "intro": "안녕하세요, 그리고 디자인하는 히밍(heeming) 입니다."}, "S13": {"instagram": "https://www.instagram.com/heeheeclub_official/", "website": "https://smartstore.naver.com/doyouand", "intro": "반짝 웃음 하나면, 어디든 히히클럽!\n\nHappy Emotion Everywhere,\nHearts Enjoy Everyday."}, "L38": {"instagram": "https://www.instagram.com/ayaminakazawa/", "website": "http://rakuentokyo.com", "intro": "일본의 일러스트레이터.\n'영화 같은 밤'을 주제로 일본의 야경을 그리고 있습니다. 주요 실적은 일본에서의 뮤직비디오, 의류, 굿즈 일러스트 등입니다."}, "K34": {"instagram": "https://www.instagram.com/archiestudio/", "website": "https://archie-studio.com", "intro": "An illustrator and designer who grew up in Bangkok and currently lives between Bangkok —  London."}, "F15": {"instagram": "https://www.instagram.com/bk529_art/", "intro": "안녕하세요\n그리고 싶은 것을 그리고 디자인합니다."}, "P33": {"instagram": "https://www.instagram.com/bunman_eggo?utm_source=ig_web_button_share_sheet&igsh=ZDNlZDc0MzIxNw==", "intro": "Hello! Welcome to Bunman's Bakery! We make yummy freshly baked bread here~"}, "J29": {"instagram": "https://www.instagram.com/tangxiao_manga/", "intro": "Hi! I am a manga artist from China."}, "O42": {"website": "caringwong.com"}, "K31": {"instagram": "https://www.instagram.com/danni_litblue/", "intro": "런던예술대학교에서 시각 커뮤니케이션과 일러스트레이션을 전공하고 2024년 졸업한 전문 일러스트레이터입니다. 그녀는 광물 안료와 숯의 독특한 질감을 탐구하며, 섬세한 필치와 서사적"}, "P32": {"instagram": "https://www.instagram.com/dogdogbengpeng/", "intro": "Colorful, delicious, fun, and cute – let these become my daily routine!"}, "N32": {"instagram": "https://www.instagram.com/doromon01/", "website": "https://doromon01.com/", "intro": "대만 기반의 일러스트 브랜드 'Doromon Plantimals'입니다. 식물과 동물의 매력을 결합해 탄생시킨 귀여운 'Plantimals' 캐릭터들을 선보이고 있습니다."}, "R15": {"instagram": "https://www.instagram.com/_in_the_fairytale._?igsh=MTY1Y2M1NnlzbzRsag%3D%3D&utm_source=qr", "intro": "Shh.. fairies sleep here.."}, "O26": {"website": "https://faraphicstudio.myportfolio.com/"}, "R06": {"instagram": "https://www.instagram.com/gapnstudio/", "website": "https://x.com/GapnStudio", "intro": "Hi!! This is GapN studio from Thailand! with my original character 'Lamud' the brown bear"}, "P31": {"instagram": "https://www.instagram.com/get.mars?igsh=MWI2bnV5ZWRvMmY5OA%3D%3D&utm_source=qr", "website": "https://x.com/getgetget48?s=11", "intro": "GET.MARS is a Thai illustrator creating original hedgehog characters and cozy, whimsical artwork."}, "H05": {"instagram": "https://www.instagram.com/illustrator_haemil", "website": "https://blog.naver.com/ariel8132", "intro": "디지털 드로잉부터 수작업까지 다양한 작업을 이어가는 일러스트레이터입니다.  일러스트·페이퍼아트·팝업북·문화예술교육으로 예술이 일상에 스며드는 순간을 만들어갑니다."}, "K11": {"instagram": "www.instagram.com/herbijouu", "website": "www.herdiniaprilia.com", "intro": "Herdini Aprilia is an Indonesian illustrator and the founder of Her Bijou, a Local Brand inIndonesia"}, "P43": {"instagram": "https://www.instagram.com/sitong.liu_ener08/", "intro": "Illustrator and brand designer."}, "F31": {"instagram": "https://www.instagram.com/j_han_gg", "website": "https://hanjiyon.com/", "intro": "대작을 남기고 싶습니다"}, "H25": {"instagram": "https://www.instagram.com/judejudejude00/", "website": "https://x.com/judejudejude01", "intro": "JUDE정수진\n동물과 인간, 기억과 풍경의 관계를 관찰하며 작업한다.\n오랫동안 함께 살았던 반려토끼 크림이를 계기로 토끼를 그리기 시작했다."}, "J42": {"website": "https://kooklesart.com", "intro": "Original IP: Giri Chan, a cute little triangle rice ball with a curious and adventurous spirit."}, "J40": {"instagram": "https://www.instagram.com/lepetitmonsieur_11/", "intro": "I’m Le Petit Monsieur a French artist.\n\nDraw to soothe, made to smile"}, "J39": {"instagram": "https://www.instagram.com/fan.kimiko.chang16?igsh=cG0wa2djMzZzMzds&utm_source=qr", "website": "https://www.facebook.com/profile.php?id=100073451622275", "intro": "Illustrator Fan Kimiko, creator of “Little Couple,” sharing love and gentle healing through art."}, "M46": {"instagram": "https://www.instagram.com/fromlooptobegins?igsh=eTRtbDlhdG1heWFp&utm_source=qr", "intro": "룹비긴즈는 작고 사랑스러운 일상으로 모두에게 작은 치유를 전하고자 합니다.\n계절마다 다른 주제로 일상의 아름다움을 표현하며, 부드러운 색감과 단순한 디자인의 캐릭터, 그리고 각 테"}, "M08": {"instagram": "https://www.instagram.com/manting_illustration/", "website": "https://manting1027.wixsite.com/mantingsartwork", "intro": "Create Landscapes full of imagination and emotional sensitivity."}, "P35": {"instagram": "https://www.instagram.com/mayuuatelier", "website": "https://mayuu.main.jp/", "intro": "Hi,  저는 어린이용 학습 그림책 등의 일러스트레이터입니다.  해외 첫 출점이라서 설레고 있습니다. 꼭 작품을 보러 와 주시기 바랍니다!\n만나 뵙기를 기대하고 있습니다."}, "K35": {"instagram": "www.instagram.com/memiann.studio", "website": "www.x.com/memiannstudio", "intro": "Whimsical and weirdly adorable monsters, here to make your everyday a little brighter :)"}, "I44": {"instagram": "https://www.instagram.com/mmtostudio?igsh=a2NjYTRva3ptbTht", "intro": "I am a painter from China.\nLike drawing and handicrafts"}, "V28": {"website": "https://moggymansions.com", "intro": "London based stationery business selling handmade goods designed by us"}, "O43": {"instagram": "https://www.instagram.com/mutobread_/", "website": "https://x.com/mutoforest_oc", "intro": "Taiwanese!\nLove drawing\nmaking little stuff"}, "H49": {"instagram": "https://www.instagram.com/nayu.y2?igsh=cmdkbjVkc2FubHoz&utm_source=qr", "intro": "Nayuz 나유즈\n몽글몽글 하늘에서 찾아온 작은 천사 친구들, 나유즈! ☁️💙 사랑스러운 표정으로 하루에 작은 행복을 선물해요."}, "N52": {"instagram": "https://www.instagram.com/rinrin.cioccomoca/", "website": "https://cioccomoca.com", "intro": "🌈네코랜드는 무지개를 발견한 고양이들이 구름 위에서 즐겁고 평화롭게 사는 세계입니다. 만약 당신의 귀여운 가족도 함께라면, 분명 사이좋게 즐거운 시간을 보내고 있을 거예요🌈"}, "O06": {"instagram": "https://www.instagram.com/nuomi0213/", "website": "https://www.facebook.com/chenNuomi"}, "N15": {"instagram": "https://www.instagram.com/ouncestudio/", "website": "https://www.ounce-studio.com/", "intro": "Leslie believes the culture of food should be celebrated, the sense of taste could be visualized."}, "P30": {"instagram": "instagram.com/papergoodsbydorie", "website": "papergoodsbydorie.com", "intro": "홍콩 브랜드 일상에서 영감받은 도장, 스티커 등 문구 굿즈를 선보입니다. 특히 직장인들의 큰 공감을 자아내는 오리지널 집순이 캐릭터 사랑받고 있습니다."}, "J44": {"instagram": "https://www.instagram.com/parrotdaylifeillustration/", "website": "www.parrotdaylife.com"}, "I51": {"instagram": "https://www.instagram.com/aranegapaula/", "website": "https://www.behance.net/paulaaranega2", "intro": "📷개인 인스타그램: @paulaaranega\n🎨아트 인스타그램: @aranegapaula\n🍀업무 및 협업 문의: paulaaranegagonzalez@gmail.com"}, "O40": {"instagram": "https://www.instagram.com/jin.pinko", "website": "https://www.xiaohongshu.com/user/profile/5cb9674e000000001701de2d?xsec_token=YBsJebjxnF8Ps9rXX5UTaeJf0kyvk9H9SM3r8atzYAy-Y=&xsec_source=app_share&xhsshare=CopyLink&shareRedId=N0lEOTk8OE42NzUyOTgwNjc6OThISjhN&apptime=1775723128&share_id=85d289d08d964e78b8ab55a396cbe835", "intro": "love summer"}, "H36": {"instagram": "https://www.instagram.com/planetbear_cn/", "website": "https://shop101613755.taobao.com/category.htm?spm=pc_detail.30350276.shop_block.dshopinfo.181241d745a2DB", "intro": "Welcome to Bear Cafe!\nRun by PanPan and friends,Bear Cafe is a cozy little coffee shop in Bear Town."}, "I42": {"instagram": "www.instagram.com/raaqueelc", "website": "www.raquelpcruz.com", "intro": "I am a Honduran artist living in Vietnam. I love to make colorful art inspired by my cats,"}, "Q06": {"instagram": "https://www.instagram.com/rin.jakkavan", "website": "https://rinjirajakkavan.com/", "intro": "Illustrator based in Thailand"}, "J30": {"instagram": "https://www.instagram.com/rynisyou/", "website": "https://rynisyou.com/", "intro": "SIFV.21 @ J30 !"}, "L14": {"instagram": "www.instagram.com/shinb.art", "intro": "삶과 죽음의 경계에서 나를 찾는 선의 여행"}, "N13": {"instagram": "https://www.instagram.com/song.soong.sooong/", "intro": "A playful world where Hebby and friends turn everyday moments into joyful stories."}, "N11": {"instagram": "https://www.instagram.com/sunipaidui_/", "intro": "instagram @sunipaidui_\nillustrator / Taiwan"}, "N47": {"instagram": "instagram.com/thankqforbrunchh"}, "O39": {"instagram": "https://www.instagram.com/the.creamy.petals_studio?igsh=bzVqems3b3Frcnpx&utm_source=qr", "website": "https://hk.pinkoi.com/store/thecreamypetals", "intro": "HK illustrator creating daily doses of joy with cute bear Ollie & bird Rosie."}, "J41": {"instagram": "https://www.instagram.com/todayfor_han/", "intro": "Hi everyone! I'm Ahan☆\nYellow thing is GuaiGuai!\nWelcome to Guai Universe!"}, "O44": {"instagram": "https://www.instagram.com/tomoewhat77/", "website": "https://linktr.ee/tomoewhat77", "intro": "creator from Taiwan"}, "N16": {"instagram": "https://www.instagram.com/artwork_tong/"}, "O04": {"instagram": "https://www.instagram.com/weeeee90sbaby?igsh=MXAyYTV5dDJ5NTN2aw%3D%3D&utm_source=qr", "intro": "Weeeee! 是一個結合角色故事與手工設計的獨立品牌，擅長把動物角色的幽默、療癒日常轉譯成包包、娃娃實用的商品。從麻吉耳機包到創意收納系列，每件作品都帶著童年的玩心，讓可愛陪伴日常。"}, "J17": {"instagram": "instagram.com/whereskim.co/", "intro": "Two artists making small-batch goods for big-feeling people."}, "J43": {"instagram": "https://www.instagram.com/hedy1301lin?r=nametag", "website": "https://www.facebook.com/Hedy0428/", "intro": "그림은 저와 내면, 그리고 세상과 소통하는 방식입니다."}, "N14": {"instagram": "https://www.instagram.com/aimeeliuart", "website": "https://yongdanstudio.com", "intro": "Taiwanese brand sharing poetic, heartfelt illustrations of women, children, and everyday life."}, "O32": {"website": "https://zerotype.crd.co/", "intro": "Designer creating nostalgic, retro-futuristic artwork and premium items for gamers and hobbyists."}}